Assignments/Verilog Assignments/Assignment 5/5.1/Automatic_Garage_Door_Controller.v
module Automatic_Garage_Door_Controller (
    input UP_Max,DN_Max,
    input Activate,
    input CLK,RST,
    output UP_M,DN_M
);
    localparam [1:0] IDLE_state = 0,
                Mv_Up_state = 1,
                Mv_Dn_state = 2;
    reg [1:0] next_state,current_state;
    always @(posedge CLK or negedge RST) begin
        if (!RST) begin
            current_state <= IDLE_state;
        end
        else
            current_state <= next_state;
    end
    assign UP_M = current_state == Mv_Up_state;
    assign DN_M = current_state == Mv_Dn_state;
    always @(*) begin
        next_state = IDLE_state;
        case (current_state)
            IDLE_state: 
                if (!Activate) begin
                    next_state = IDLE_state;
                end
                else if (UP_Max && !DN_Max) begin
                    next_state = Mv_Dn_state;
                end
                else if (!UP_Max && DN_Max) begin
                    next_state = Mv_Up_state;
                end
                else
                    next_state = IDLE_state;
            Mv_Up_state: 
                if (UP_Max) begin
                    next_state = IDLE_state;
                end
                else
                    next_state = Mv_Up_state;
            Mv_Dn_state: 
                if (DN_Max) begin
                    next_state = IDLE_state;
                end
                else
                    next_state = Mv_Dn_state;
        endcase
    end
endmodule //Automatic_Garage_Door_Controller

Assignments/Verilog Assignments/Assignment 5/5.1/Automatic_Garage_Door_Controller_TB.v
`timescale 1ns/1ps

module Automatic_Garage_Door_Controller_TB;

    //-------------------------------------------------------------------------
    // Parameters
    //-------------------------------------------------------------------------
    localparam CLK_PERIOD = 20; // 50 MHz -> 20 ns period
    
    // DUT internal state encoding (must match the design)
    localparam [1:0] IDLE_state  = 2'b00;
    localparam [1:0] Mv_Up_state = 2'b01;
    localparam [1:0] Mv_Dn_state = 2'b10;

    //-------------------------------------------------------------------------
    // Signals
    //-------------------------------------------------------------------------
    reg  UP_Max_TB;
    reg  DN_Max_TB;
    reg  Activate_TB;
    reg  CLK_TB;
    reg  RST_TB;
    
    wire UP_M_TB;
    wire DN_M_TB;
    
    // Test tracking counters
    integer test_num = 0;
    integer passed   = 0;
    integer failed   = 0;

    //-------------------------------------------------------------------------
    // DUT Instantiation
    //-------------------------------------------------------------------------
    Automatic_Garage_Door_Controller DUT (
        .UP_Max   (UP_Max_TB),
        .DN_Max   (DN_Max_TB),
        .Activate (Activate_TB),
        .CLK      (CLK_TB),
        .RST      (RST_TB),
        .UP_M     (UP_M_TB),
        .DN_M     (DN_M_TB)
    );

    //-------------------------------------------------------------------------
    // Clock Generation: 50 MHz (20 ns period)
    //-------------------------------------------------------------------------
    initial begin
        CLK_TB = 0;
        forever #(CLK_PERIOD / 2) CLK_TB = ~CLK_TB;
    end

    //-------------------------------------------------------------------------
    // Timeout Watchdog (safety net if DUT hangs)
    //-------------------------------------------------------------------------
    initial begin
        #5000;
        $display("[TIMEOUT] Simulation exceeded limit. Terminating.");
        $finish;
    end

    //-------------------------------------------------------------------------
    // Tasks
    //-------------------------------------------------------------------------
    
    // Apply asynchronous reset (active-low)
    task apply_reset;
        begin
            $display("[INFO] Applying asynchronous reset...");
            RST_TB = 0;
            #(CLK_PERIOD * 2);
            RST_TB = 1;
            #(CLK_PERIOD);
        end
    endtask

    // Drive inputs at negedge (clean setup time before next posedge)
    task drive_inputs;
        input up_max;
        input dn_max;
        input activate;
        begin
            @(negedge CLK_TB);
            UP_Max_TB   = up_max;
            DN_Max_TB   = dn_max;
            Activate_TB = activate;
        end
    endtask

    // Check state and outputs at negedge (stable sampling point)
    // Hierarchical reference DUT.current_state lets us verify the internal state.
    task check_state_outputs;
        input [1:0]    exp_state;
        input          exp_up_m;
        input          exp_dn_m;
        input [8*64:1] test_name;
        begin
            @(negedge CLK_TB);
            test_num = test_num + 1;
            
            if (DUT.current_state !== exp_state) begin
                $error("TEST %0d FAILED: %-45s | Expected state=%b, Got state=%b @ %0t",
                       test_num, test_name, exp_state, DUT.current_state, $time);
                failed = failed + 1;
            end
            else if (UP_M_TB !== exp_up_m) begin
                $error("TEST %0d FAILED: %-45s | Expected UP_M=%b, Got UP_M=%b @ %0t",
                       test_num, test_name, exp_up_m, UP_M_TB, $time);
                failed = failed + 1;
            end
            else if (DN_M_TB !== exp_dn_m) begin
                $error("TEST %0d FAILED: %-45s | Expected DN_M=%b, Got DN_M=%b @ %0t",
                       test_num, test_name, exp_dn_m, DN_M_TB, $time);
                failed = failed + 1;
            end
            else begin
                $display("TEST %0d PASSED: %-45s @ %0t", test_num, test_name, $time);
                passed = passed + 1;
            end
        end
    endtask

    //-------------------------------------------------------------------------
    // Main Test Sequence
    //-------------------------------------------------------------------------
    initial begin
        $display("================================================================================");
        $display("          Automatic Garage Door Controller - Self-Checking Testbench");
        $display("================================================================================");
        $display("[INFO] Clock Period = %0d ns (50 MHz)", CLK_PERIOD);
        $display("");

        // Initialize inputs to safe defaults
        UP_Max_TB   = 0;
        DN_Max_TB   = 0;
        Activate_TB = 0;

        //---------------------------------------------------------------------
        // 1. Power-on / Asynchronous Reset
        //---------------------------------------------------------------------
        apply_reset;
        check_state_outputs(IDLE_state, 1'b0, 1'b0, "Async Reset -> IDLE");

        //---------------------------------------------------------------------
        // 2. IDLE hold when Activate = 0 (door is down)
        //---------------------------------------------------------------------
        drive_inputs(0, 1, 0); // DN_Max=1 (door fully closed), Activate=0
        check_state_outputs(IDLE_state, 1'b0, 1'b0, "IDLE hold (Activate=0)");

        //---------------------------------------------------------------------
        // 3. IDLE -> Mv_Up: Door is down, user presses Activate
        //---------------------------------------------------------------------
        drive_inputs(0, 1, 1); // DN_Max=1, Activate=1
        check_state_outputs(Mv_Up_state, 1'b1, 1'b0, "IDLE -> Mv_Up (open door)");

        //---------------------------------------------------------------------
        // 4. Mv_Up holds while door is moving (UP_Max=0)
        //    In a Moore machine, Activate and DN_Max are don't-cares here.
        //---------------------------------------------------------------------
        drive_inputs(0, 0, 0); // UP_Max=0, DN_Max=0, Activate=0
        check_state_outputs(Mv_Up_state, 1'b1, 1'b0, "Mv_Up hold (UP_Max=0)");

        //---------------------------------------------------------------------
        // 5. Mv_Up -> IDLE: Door fully open (UP_Max=1)
        //---------------------------------------------------------------------
        drive_inputs(1, 0, 0); // UP_Max=1
        check_state_outputs(IDLE_state, 1'b0, 1'b0, "Mv_Up -> IDLE (UP_Max=1)");

        //---------------------------------------------------------------------
        // 6. IDLE -> Mv_Dn: Door is up, user presses Activate
        //---------------------------------------------------------------------
        drive_inputs(1, 0, 1); // UP_Max=1, Activate=1
        check_state_outputs(Mv_Dn_state, 1'b0, 1'b1, "IDLE -> Mv_Dn (close door)");

        //---------------------------------------------------------------------
        // 7. Mv_Dn holds while door is moving (DN_Max=0)
        //    In a Moore machine, Activate and UP_Max are don't-cares here.
        //---------------------------------------------------------------------
        drive_inputs(0, 0, 0); // DN_Max=0, Activate=0
        check_state_outputs(Mv_Dn_state, 1'b0, 1'b1, "Mv_Dn hold (DN_Max=0)");

        //---------------------------------------------------------------------
        // 8. Mv_Dn -> IDLE: Door fully closed (DN_Max=1)
        //---------------------------------------------------------------------
        drive_inputs(0, 1, 0); // DN_Max=1
        check_state_outputs(IDLE_state, 1'b0, 1'b0, "Mv_Dn -> IDLE (DN_Max=1)");

        //---------------------------------------------------------------------
        // 9. Broken sensor: both sensors low, Activate=1 -> must stay IDLE
        //---------------------------------------------------------------------
        drive_inputs(0, 0, 1); // Both 0, Activate=1
        check_state_outputs(IDLE_state, 1'b0, 1'b0, "IDLE hold (both sensors low)");

        //---------------------------------------------------------------------
        // 10. Broken sensor: both sensors high, Activate=1 -> must stay IDLE
        //---------------------------------------------------------------------
        drive_inputs(1, 1, 1); // Both 1, Activate=1
        check_state_outputs(IDLE_state, 1'b0, 1'b0, "IDLE hold (both sensors high)");

        //---------------------------------------------------------------------
        // 11. Mv_Up ignores Activate while moving (Activate=1, UP_Max=0)
        //---------------------------------------------------------------------
        // First enter Mv_Up
        drive_inputs(0, 1, 1); // DN_Max=1, Activate=1 -> next state Mv_Up
        check_state_outputs(Mv_Up_state, 1'b1, 1'b0, "Enter Mv_Up for ignore test");
        // Now keep Activate=1 while door is still moving (UP_Max=0)
        drive_inputs(0, 0, 1); // UP_Max=0, Activate=1
        check_state_outputs(Mv_Up_state, 1'b1, 1'b0, "Mv_Up ignores Activate");

        //---------------------------------------------------------------------
        // 12. Mv_Dn ignores Activate while moving (Activate=1, DN_Max=0)
        //---------------------------------------------------------------------
        // Finish opening first
        drive_inputs(1, 0, 0); // UP_Max=1 -> IDLE
        check_state_outputs(IDLE_state, 1'b0, 1'b0, "Return to IDLE");
        // Enter Mv_Dn
        drive_inputs(1, 0, 1); // UP_Max=1, Activate=1 -> Mv_Dn
        check_state_outputs(Mv_Dn_state, 1'b0, 1'b1, "Enter Mv_Dn for ignore test");
        // Keep Activate=1 while door is still moving (DN_Max=0)
        drive_inputs(0, 0, 1); // DN_Max=0, Activate=1
        check_state_outputs(Mv_Dn_state, 1'b0, 1'b1, "Mv_Dn ignores Activate");

        //---------------------------------------------------------------------
        // 13. Asynchronous reset from Mv_Dn (asserted mid-cycle)
        //---------------------------------------------------------------------
        // Ensure we are in Mv_Dn
        drive_inputs(1, 0, 1); // UP_Max=1, Activate=1 -> next state Mv_Dn
        @(negedge CLK_TB); // Wait for stable state
        #5; // Move to middle of cycle (async reset must work without clock)
        RST_TB = 0;
        #1; // Propagation delay
        test_num = test_num + 1;
        if (DUT.current_state !== IDLE_state || UP_M_TB !== 0 || DN_M_TB !== 0) begin
            $error("TEST %0d FAILED: %-45s | Expected IDLE/00, Got state=%b UP_M=%b DN_M=%b @ %0t",
                   test_num, "Async Reset from Mv_Dn", DUT.current_state, UP_M_TB, DN_M_TB, $time);
            failed = failed + 1;
        end else begin
            $display("TEST %0d PASSED: %-45s @ %0t", test_num, "Async Reset from Mv_Dn", $time);
            passed = passed + 1;
        end
        RST_TB = 1;
        // CRITICAL FIX: After releasing reset, stale inputs (UP_Max=1, Activate=1)
        // would cause IDLE->Mv_Dn on the next clock edge. Drive safe inputs first
        // to establish a known IDLE baseline before the next test.
        drive_inputs(0, 1, 0); // DN_Max=1, Activate=0 -> stay in IDLE
        check_state_outputs(IDLE_state, 1'b0, 1'b0, "IDLE cleanup after async reset");

        //---------------------------------------------------------------------
        // 14. Asynchronous reset from Mv_Up (asserted mid-cycle)
        //---------------------------------------------------------------------
        // Enter Mv_Up from known IDLE (door down)
        drive_inputs(0, 1, 1); // DN_Max=1, Activate=1 -> Mv_Up
        check_state_outputs(Mv_Up_state, 1'b1, 1'b0, "Enter Mv_Up for reset test");
        // Assert reset mid-cycle
        @(negedge CLK_TB);
        #5;
        RST_TB = 0;
        #1;
        test_num = test_num + 1;
        if (DUT.current_state !== IDLE_state || UP_M_TB !== 0 || DN_M_TB !== 0) begin
            $error("TEST %0d FAILED: %-45s | Expected IDLE/00, Got state=%b UP_M=%b DN_M=%b @ %0t",
                   test_num, "Async Reset from Mv_Up", DUT.current_state, UP_M_TB, DN_M_TB, $time);
            failed = failed + 1;
        end else begin
            $display("TEST %0d PASSED: %-45s @ %0t", test_num, "Async Reset from Mv_Up", $time);
            passed = passed + 1;
        end
        RST_TB = 1;

        //---------------------------------------------------------------------
        // Final Summary
        //---------------------------------------------------------------------
        $display("");
        $display("================================================================================");
        $display("                              TEST SUMMARY");
        $display("================================================================================");
        $display(" Total Tests Run : %0d", test_num);
        $display(" Passed          : %0d", passed);
        $display(" Failed          : %0d", failed);
        $display("--------------------------------------------------------------------------------");
        if (failed == 0)
            $display(" RESULT          : ALL TESTS PASSED");
        else
            $display(" RESULT          : %0d TEST(S) FAILED", failed);
        $display("================================================================================");

        $finish;
    end

    //-------------------------------------------------------------------------
    // VCD Dump for waveform debug
    //-------------------------------------------------------------------------
    initial begin
        $dumpfile("Automatic_Garage_Door_Controller_TB.vcd");
        $dumpvars(0, Automatic_Garage_Door_Controller_TB);
    end

endmodule

Assignments/Verilog Assignments/Assignment 5/5.1/Automatic_Garage_Door_Controller_TB.vcd
$date
	Sun Jul 26 09:40:29 2026
$end
$version
	ModelSim Version 2020.1
$end
$timescale
	1ps
$end

$scope module Automatic_Garage_Door_Controller_TB $end
$var parameter 32 ! CLK_PERIOD $end
$var parameter 2 " IDLE_state $end
$var parameter 2 # Mv_Up_state $end
$var parameter 2 $ Mv_Dn_state $end
$var reg 1 % UP_Max_TB $end
$var reg 1 & DN_Max_TB $end
$var reg 1 ' Activate_TB $end
$var reg 1 ( CLK_TB $end
$var reg 1 ) RST_TB $end
$var wire 1 * UP_M_TB $end
$var wire 1 + DN_M_TB $end
$var integer 32 , test_num $end
$var integer 32 - passed $end
$var integer 32 . failed $end

$scope task apply_reset $end
$upscope $end

$scope task drive_inputs $end
$var reg 1 / up_max $end
$var reg 1 0 dn_max $end
$var reg 1 1 activate $end
$upscope $end

$scope task check_state_outputs $end
$var reg 2 2 exp_state [1:0] $end
$var reg 1 3 exp_up_m $end
$var reg 1 4 exp_dn_m $end
$var reg 512 5 test_name [512:1] $end
$upscope $end

$scope module DUT $end
$var parameter 2 6 IDLE_state $end
$var parameter 2 7 Mv_Up_state $end
$var parameter 2 8 Mv_Dn_state $end
$var wire 1 9 UP_Max $end
$var wire 1 : DN_Max $end
$var wire 1 ; Activate $end
$var wire 1 < CLK $end
$var wire 1 = RST $end
$var wire 1 * UP_M $end
$var wire 1 + DN_M $end
$var reg 2 > next_state [1:0] $end
$var reg 2 ? current_state [1:0] $end
$upscope $end
$upscope $end
$enddefinitions $end
#0
$dumpvars
0%
0&
0'
0(
0)
b0 >
b0 ?
x/
x0
x1
bx 2
x3
x4
bx 5
b10100 !
b0 "
b1 #
b10 $
b0 6
b1 7
b10 8
b0 ,
b0 -
b0 .
0*
0+
0=
0<
0;
0:
09
$end
#10000
1(
1<
#20000
0(
0<
#30000
1(
1<
#40000
1)
0(
1=
0<
#50000
1(
1<
#60000
b0 2
03
04
b1000001011100110111100101101110011000110010000001010010011001010111001101100101011101000010000000101101001111100010000001001001010001000100110001000101 5
0(
0<
b1 ,
b1 -
0/
10
01
#70000
1(
1<
#80000
0(
0<
1&
b1001001010001000100110001000101001000000110100001101111011011000110010000100000001010000100000101100011011101000110100101110110011000010111010001100101001111010011000000101001 5
1:
#90000
1(
1<
#100000
0(
0<
b10 ,
b10 -
11
#110000
1(
1<
#120000
0(
0<
1'
b1 2
13
b1001001010001000100110001000101001000000010110100111110001000000100110101110110010111110101010101110000001000000010100001101111011100000110010101101110001000000110010001101111011011110111001000101001 5
1;
b1 >
#130000
1(
1<
b1 ?
1*
b0 >
b1 >
#140000
0(
0<
b11 ,
b11 -
00
01
#150000
1(
1<
#160000
0(
0<
0&
0'
b10011010111011001011111010101010111000000100000011010000110111101101100011001000010000000101000010101010101000001011111010011010110000101111000001111010011000000101001 5
0:
0;
b0 >
b1 >
#170000
1(
1<
#180000
0(
0<
b100 ,
b100 -
1/
#190000
1(
1<
#200000
0(
0<
1%
b0 2
03
b10011010111011001011111010101010111000000100000001011010011111000100000010010010100010001001100010001010010000000101000010101010101000001011111010011010110000101111000001111010011000100101001 5
19
b0 >
#210000
1(
1<
b0 ?
0*
#220000
0(
0<
b101 ,
b101 -
11
#230000
1(
1<
#240000
0(
0<
1'
b10 2
14
b100100101000100010011000100010100100000001011010011111000100000010011010111011001011111010001000110111000100000001010000110001101101100011011110111001101100101001000000110010001101111011011110111001000101001 5
1;
b10 >
#250000
1(
1<
b10 ?
1+
b0 >
b10 >
#260000
0(
0<
b110 ,
b110 -
0/
01
#270000
1(
1<
#280000
0(
0<
0%
0'
b10011010111011001011111010001000110111000100000011010000110111101101100011001000010000000101000010001000100111001011111010011010110000101111000001111010011000000101001 5
09
0;
b0 >
b10 >
#290000
1(
1<
#300000
0(
0<
b111 ,
b111 -
10
#310000
1(
1<
#320000
0(
0<
1&
b0 2
04
b10011010111011001011111010001000110111000100000001011010011111000100000010010010100010001001100010001010010000000101000010001000100111001011111010011010110000101111000001111010011000100101001 5
1:
b0 >
#330000
1(
1<
b0 ?
0+
#340000
0(
0<
b1000 ,
b1000 -
00
11
#350000
1(
1<
#360000
0(
0<
0&
1'
b1001001010001000100110001000101001000000110100001101111011011000110010000100000001010000110001001101111011101000110100000100000011100110110010101101110011100110110111101110010011100110010000001101100011011110111011100101001 5
0:
1;
#370000
1(
1<
#380000
0(
0<
b1001 ,
b1001 -
1/
10
#390000
1(
1<
#400000
0(
0<
1%
1&
b100100101000100010011000100010100100000011010000110111101101100011001000010000000101000011000100110111101110100011010000010000001110011011001010110111001110011011011110111001001110011001000000110100001101001011001110110100000101001 5
19
1:
#410000
1(
1<
#420000
0(
0<
b1010 ,
b1010 -
0/
#430000
1(
1<
#440000
0(
0<
0%
b1 2
13
b10001010110111001110100011001010111001000100000010011010111011001011111010101010111000000100000011001100110111101110010001000000110100101100111011011100110111101110010011001010010000001110100011001010111001101110100 5
09
b1 >
#450000
1(
1<
b1 ?
1*
b0 >
b1 >
#460000
0(
0<
b1011 ,
b1011 -
00
#470000
1(
1<
#480000
0(
0<
0&
b1001101011101100101111101010101011100000010000001101001011001110110111001101111011100100110010101110011001000000100000101100011011101000110100101110110011000010111010001100101 5
0:
b0 >
b1 >
#490000
1(
1<
#500000
0(
0<
b1100 ,
b1100 -
1/
01
#510000
1(
1<
#520000
0(
0<
1%
0'
b0 2
03
b101001001100101011101000111010101110010011011100010000001110100011011110010000001001001010001000100110001000101 5
19
0;
b0 >
#530000
1(
1<
b0 ?
0*
#540000
0(
0<
b1101 ,
b1101 -
11
#550000
1(
1<
#560000
0(
0<
1'
b10 2
14
b10001010110111001110100011001010111001000100000010011010111011001011111010001000110111000100000011001100110111101110010001000000110100101100111011011100110111101110010011001010010000001110100011001010111001101110100 5
1;
b10 >
#570000
1(
1<
b10 ?
1+
b0 >
b10 >
#580000
0(
0<
b1110 ,
b1110 -
0/
#590000
1(
1<
#600000
0(
0<
0%
b1001101011101100101111101000100011011100010000001101001011001110110111001101111011100100110010101110011001000000100000101100011011101000110100101110110011000010111010001100101 5
09
b0 >
b10 >
#610000
1(
1<
#620000
0(
0<
b1111 ,
b1111 -
1/
#630000
1(
1<
#640000
0(
0<
1%
19
b0 >
b10 >
#650000
1(
1<
#660000
0(
0<
#665000
0)
0=
b0 ?
0+
b0 >
b10 >
#666000
b10000 ,
b10000 -
1)
0/
10
01
1=
#670000
1(
1<
b10 ?
1+
b0 >
b10 >
#680000
0(
0<
0%
1&
0'
b0 2
04
b10010010100010001001100010001010010000001100011011011000110010101100001011011100111010101110000001000000110000101100110011101000110010101110010001000000110000101110011011110010110111001100011001000000111001001100101011100110110010101110100 5
09
1:
0;
b0 >
#690000
1(
1<
b0 ?
0+
#700000
0(
0<
b10001 ,
b10001 -
11
#710000
1(
1<
#720000
0(
0<
1'
b1 2
13
b100010101101110011101000110010101110010001000000100110101110110010111110101010101110000001000000110011001101111011100100010000001110010011001010111001101100101011101000010000001110100011001010111001101110100 5
1;
b1 >
#730000
1(
1<
b1 ?
1*
b0 >
b1 >
#740000
0(
0<
b10010 ,
b10010 -
#750000
1(
1<
#760000
0(
0<
#765000
0)
0=
b0 ?
0*
b0 >
b1 >
#766000
b10011 ,
b10011 -
1)
