Assignments/Verilog Assignments/Assignment 3/ALU.v
module ALU(
    input [15:0] A,B,
    input [3:0] ALU_FUN,
    input CLK,
    output reg [15:0] ALU_OUT,
    output reg Carry_Flag,
    output Arith_Flag,Logic_Flag,CMP_Flag,Shift_Flag
);
    reg [15:0] ALU_OUT_Comb;
    assign  Arith_Flag = (!ALU_FUN[2] && !ALU_FUN[3]),
            Logic_Flag = (!ALU_FUN[3] && ALU_FUN[2]) || (ALU_FUN[3] && !ALU_FUN[2] && !ALU_FUN[1]),
            CMP_Flag = (ALU_FUN[3] && !ALU_FUN[2] && ALU_FUN[1]) || (ALU_FUN[3] && ALU_FUN[2] && !ALU_FUN[1] && !ALU_FUN[0]),
            Shift_Flag = (ALU_FUN[3] && ALU_FUN[2] && !ALU_FUN[1] && ALU_FUN[0]) || (ALU_FUN[3] && ALU_FUN[2] && ALU_FUN[1] && !ALU_FUN[0]);
    always @(posedge CLK) begin
        ALU_OUT <= ALU_OUT_Comb;
    end
    always @(*) begin
        Carry_Flag = 0; // default value
        case (ALU_FUN)
            4'b0000: {Carry_Flag, ALU_OUT_Comb} = {1'b0, A} + {1'b0, B};
            4'b0001: {Carry_Flag, ALU_OUT_Comb} = {1'b0, A} - {1'b0, B};
            4'b0010: ALU_OUT_Comb = A * B;
            4'b0011: ALU_OUT_Comb = A / B;
            4'b0100: ALU_OUT_Comb = A & B;
            4'b0101: ALU_OUT_Comb = A | B;
            4'b0110: ALU_OUT_Comb = ~(A & B);
            4'b0111: ALU_OUT_Comb = ~(A | B);
            4'b1000: ALU_OUT_Comb = (A ^ B);
            4'b1001: ALU_OUT_Comb = (A ~^ B);
            4'b1010: ALU_OUT_Comb = (A == B) ? 16'd1 : 16'd0;
            4'b1011: ALU_OUT_Comb = (A > B)  ? 16'd2 : 16'd0;
            4'b1100: ALU_OUT_Comb = (A < B)  ? 16'd3 : 16'd0;
            4'b1101: ALU_OUT_Comb = A >> 1;
            4'b1110: ALU_OUT_Comb = A << 1;
            default: ALU_OUT_Comb = 0;
        endcase
    end
endmodule

Assignments/Assignment 3/testbench.v
`timescale 1us/1ns
module ALU_TB;
    reg [15:0] A_TB,B_TB;
    reg [3:0] ALU_FUN_TB;
    reg CLK_TB;
    wire [15:0] ALU_OUT_TB;
    wire Carry_Flag_TB,Arith_Flag_TB,Logic_Flag_TB,CMP_Flag_TB,Shift_Flag_TB;
    ALU DUT_ALU (
        .A(A_TB),.B(B_TB),
        .ALU_FUN(ALU_FUN_TB),
        .CLK(CLK_TB),
        .ALU_OUT(ALU_OUT_TB),
        .Carry_Flag(Carry_Flag_TB),.Arith_Flag(Arith_Flag_TB),.Logic_Flag(Logic_Flag_TB),.CMP_Flag(CMP_Flag_TB),.Shift_Flag(Shift_Flag_TB)
    );
    initial begin
        CLK_TB = 0;
        forever begin
            #5 CLK_TB = ~CLK_TB;
        end
    end
    initial begin
        $monitor("At Time: %0t,ALU_OUT: %0b_%0b_%b_%0b,C_F: %0b,A_F: %0b,L_F: %0b,CMP_F: %0b,S_F: %0b",$time
                ,ALU_OUT_TB[15:12],ALU_OUT_TB[11:8],ALU_OUT_TB[7:4],ALU_OUT_TB[3:0]
                ,Carry_Flag_TB,Arith_Flag_TB,Logic_Flag_TB,CMP_Flag_TB,Shift_Flag_TB);
    end
    initial begin
        $dumpfile("ALU_TB.vcd");
        $dumpvars;
    end
    initial fork 
        A_TB = 16'hF;B_TB = 16'hF;ALU_FUN_TB = 4'h0;
        // Base Cases
        #10 ALU_FUN_TB = 4'h1;
        #20 ALU_FUN_TB = 4'h2;
        #30 ALU_FUN_TB = 4'h3;
        #40 ALU_FUN_TB = 4'h4;
        #50 ALU_FUN_TB = 4'h5;
        #60 ALU_FUN_TB = 4'h6;
        #70 ALU_FUN_TB = 4'h7;
        #80 ALU_FUN_TB = 4'h8;
        #90 ALU_FUN_TB = 4'h9;
        #100 ALU_FUN_TB = 4'hA;
        #110 ALU_FUN_TB = 4'hB;
        #120 ALU_FUN_TB = 4'hC;
        #130 ALU_FUN_TB = 4'hD;
        #140 ALU_FUN_TB = 4'hE;
        #150 ALU_FUN_TB = 4'hF;
        // Corner Cases
        #160 A_TB = 16'h8000;#160 B_TB = 16'h8000;
        #170 ALU_FUN_TB = 4'h0; // Carry Test Addition
        #180 A_TB = 16'h0000;#180 B_TB = 16'h8000;
        #190 ALU_FUN_TB = 4'h1; // Carry Test Subtracion,Smaller Than
        #200 A_TB = 16'h1000;#200 B_TB = 16'h0100;
        #210 ALU_FUN_TB = 4'b1011; // A > B
        #220 A_TB = 16'h8000;#220 ALU_FUN_TB = 4'b1110; // All Zero by shift left
        #230 A_TB = 16'h0001;#230 ALU_FUN_TB = 4'b1101; // All Zero by shift right
        #250 $finish;
    join
endmodule

Assignments/Assignment 3/ALU_TB.vcd
$date
	Sun Jul 12 12:56:25 2026
$end
$version
	ModelSim Version 2020.1
$end
$timescale
	1ns
$end

$scope module ALU_TB $end
$var reg 16 ! A_TB [15:0] $end
$var reg 16 " B_TB [15:0] $end
$var reg 4 # ALU_FUN_TB [3:0] $end
$var reg 1 $ CLK_TB $end
$var wire 1 % ALU_OUT_TB [15] $end
$var wire 1 & ALU_OUT_TB [14] $end
$var wire 1 ' ALU_OUT_TB [13] $end
$var wire 1 ( ALU_OUT_TB [12] $end
$var wire 1 ) ALU_OUT_TB [11] $end
$var wire 1 * ALU_OUT_TB [10] $end
$var wire 1 + ALU_OUT_TB [9] $end
$var wire 1 , ALU_OUT_TB [8] $end
$var wire 1 - ALU_OUT_TB [7] $end
$var wire 1 . ALU_OUT_TB [6] $end
$var wire 1 / ALU_OUT_TB [5] $end
$var wire 1 0 ALU_OUT_TB [4] $end
$var wire 1 1 ALU_OUT_TB [3] $end
$var wire 1 2 ALU_OUT_TB [2] $end
$var wire 1 3 ALU_OUT_TB [1] $end
$var wire 1 4 ALU_OUT_TB [0] $end
$var wire 1 5 Carry_Flag_TB $end
$var wire 1 6 Arith_Flag_TB $end
$var wire 1 7 Logic_Flag_TB $end
$var wire 1 8 CMP_Flag_TB $end
$var wire 1 9 Shift_Flag_TB $end

$scope module DUT_ALU $end
$var wire 1 : A [15] $end
$var wire 1 ; A [14] $end
$var wire 1 < A [13] $end
$var wire 1 = A [12] $end
$var wire 1 > A [11] $end
$var wire 1 ? A [10] $end
$var wire 1 @ A [9] $end
$var wire 1 A A [8] $end
$var wire 1 B A [7] $end
$var wire 1 C A [6] $end
$var wire 1 D A [5] $end
$var wire 1 E A [4] $end
$var wire 1 F A [3] $end
$var wire 1 G A [2] $end
$var wire 1 H A [1] $end
$var wire 1 I A [0] $end
$var wire 1 J B [15] $end
$var wire 1 K B [14] $end
$var wire 1 L B [13] $end
$var wire 1 M B [12] $end
$var wire 1 N B [11] $end
$var wire 1 O B [10] $end
$var wire 1 P B [9] $end
$var wire 1 Q B [8] $end
$var wire 1 R B [7] $end
$var wire 1 S B [6] $end
$var wire 1 T B [5] $end
$var wire 1 U B [4] $end
$var wire 1 V B [3] $end
$var wire 1 W B [2] $end
$var wire 1 X B [1] $end
$var wire 1 Y B [0] $end
$var wire 1 Z ALU_FUN [3] $end
$var wire 1 [ ALU_FUN [2] $end
$var wire 1 \ ALU_FUN [1] $end
$var wire 1 ] ALU_FUN [0] $end
$var wire 1 ^ CLK $end
$var reg 16 _ ALU_OUT [15:0] $end
$var reg 1 ` Carry_Flag $end
$var wire 1 6 Arith_Flag $end
$var wire 1 7 Logic_Flag $end
$var wire 1 8 CMP_Flag $end
$var wire 1 9 Shift_Flag $end
$var reg 16 a ALU_OUT_Comb [15:0] $end
$upscope $end
$upscope $end
$enddefinitions $end
#0
$dumpvars
b1111 !
b1111 "
b0 #
0$
bx _
0`
b11110 a
x4
x3
x2
x1
x0
x/
x.
x-
x,
x+
x*
x)
x(
x'
x&
x%
05
16
07
08
09
0^
0]
0\
0[
0Z
1Y
1X
1W
1V
0U
0T
0S
0R
0Q
0P
0O
0N
0M
0L
0K
0J
1I
1H
1G
1F
0E
0D
0C
0B
0A
0@
0?
0>
0=
0<
0;
0:
$end
#5000
1$
1^
b11110 _
04
13
12
11
10
0/
0.
0-
0,
0+
0*
0)
0(
0'
0&
0%
#10000
b1 #
0$
1]
0^
b0 a
#15000
1$
1^
b0 _
03
02
01
00
#20000
b10 #
0$
0]
1\
0^
b11100001 a
#25000
1$
1^
b11100001 _
14
1/
1.
1-
#30000
b11 #
0$
1]
0^
b1 a
#35000
1$
1^
b1 _
0/
0.
0-
#40000
b100 #
0$
0]
0\
1[
0^
06
17
b1111 a
#45000
1$
1^
b1111 _
13
12
11
#50000
b101 #
0$
1]
0^
#55000
1$
1^
#60000
b110 #
0$
0]
1\
0^
b1111111111110000 a
#65000
1$
1^
b1111111111110000 _
04
03
02
01
10
1/
1.
1-
1,
1+
1*
1)
1(
1'
1&
1%
#70000
b111 #
0$
1]
0^
#75000
1$
1^
#80000
b1000 #
0$
0]
0\
0[
1Z
0^
b0 a
#85000
1$
1^
b0 _
00
0/
0.
0-
0,
0+
0*
0)
0(
0'
0&
0%
#90000
b1001 #
0$
1]
0^
b1111111111111111 a
#95000
1$
1^
b1111111111111111 _
14
13
12
11
10
1/
1.
1-
1,
1+
1*
1)
1(
1'
1&
1%
#100000
b1010 #
0$
0]
1\
0^
07
18
b1 a
#105000
1$
1^
b1 _
03
02
01
00
0/
0.
0-
0,
0+
0*
0)
0(
0'
0&
0%
#110000
b1011 #
0$
1]
0^
b0 a
#115000
1$
1^
b0 _
04
#120000
b1100 #
0$
0]
0\
1[
0^
#125000
1$
1^
#130000
b1101 #
0$
1]
0^
08
19
b111 a
#135000
1$
1^
b111 _
14
13
12
#140000
b1110 #
0$
0]
1\
0^
b11110 a
#145000
1$
1^
b11110 _
04
11
10
#150000
b1111 #
0$
1]
0^
09
b0 a
#155000
1$
1^
b0 _
03
02
01
00
#160000
b1000000000000000 !
b1000000000000000 "
0$
0Y
0X
0W
0V
1J
0I
0H
0G
0F
1:
0^
#165000
1$
1^
#170000
b0 #
0$
0]
0\
0[
0Z
0^
16
1`
15
#175000
1$
1^
#180000
b0 !
0$
0:
0^
0`
b1000000000000000 a
05
#185000
1$
1^
b1000000000000000 _
1%
#190000
b1 #
0$
1]
0^
1`
15
#195000
1$
1^
#200000
b1000000000000 !
b100000000 "
0$
1Q
0J
1=
0^
0`
b111100000000 a
05
#205000
1$
1^
b111100000000 _
1,
1+
1*
1)
0%
#210000
b1011 #
0$
1\
1Z
0^
06
18
b10 a
#215000
1$
1^
b10 _
13
0,
0+
0*
0)
#220000
b1000000000000000 !
b11