Assignments/Verilog Assignments/Assignment 5/5.0/CRC.v
// Port Declaration of CRC Module
module CRC (
    input DATA, ACTIVE,
    input CLK, RST,
    // Serial CRC Output
    output reg CRC,
    // Check The Output is Valid to See or No
    output reg Valid
);
    localparam [3:0] No_Registers = 8; // Set The Number of the registers
    localparam [No_Registers - 1:0] SEED = 'hD8; // RST Default Value for the Register
    localparam [No_Registers - 1:0] XOR_Bits = 'b0100_0100; // Set the XOR Gates Places

    reg [No_Registers - 1:0] LFSR;  // Registers for the algorithm and shift register
    reg [3:0] Counter;              // Counts output bits shifted so far
    integer i;
    
    wire DATA_XOR_R0_W1;  // Feedback signal
    wire Counter_Max;     // Finished shifting out all CRC bits

    assign Counter_Max = (Counter == No_Registers);
    assign DATA_XOR_R0_W1 = DATA ^ LFSR[0];

    // Outputs and registers setting
    always @(posedge CLK or negedge RST) begin
        if (!RST) begin
            LFSR  <= SEED;
            Valid <= 0;
        end
        else if (ACTIVE) begin
            Valid <= 0;
            LFSR[No_Registers - 1] <= DATA_XOR_R0_W1;
            for (i = 0; i < No_Registers - 1; i = i + 1) begin
                if (XOR_Bits[i])
                    LFSR[i] <= LFSR[i + 1] ^ DATA_XOR_R0_W1;
                else
                    LFSR[i] <= LFSR[i + 1];
            end
        end
        else if (!Counter_Max) begin
            Valid <= 1;
            CRC   <= LFSR[0];
            LFSR[No_Registers - 1] <= 0;
            for (i = 0; i < No_Registers - 1; i = i + 1) begin
                LFSR[i] <= LFSR[i + 1];
            end
        end
        else begin
            Valid <= 0;
            CRC   <= 0;
        end
    end

    // Setting the Counter
    always @(posedge CLK or negedge RST) begin
        if (!RST) begin
            Counter <= No_Registers;
        end
        else if (ACTIVE) begin
            Counter <= 0;
        end
        else if (!Counter_Max) begin
            Counter <= Counter + 1;
        end
    end
endmodule //CRC

Assignments/Verilog Assignments/Assignment 5/5.0/CRC_TB.v
`timescale 1ns/1ps
module CRC_TB;
    //-------------------------------------------------------------------------
    // Parameters
    //-------------------------------------------------------------------------
    localparam CLK_PERIOD   = 100; // 10 MHz -> 100 ns period
    localparam No_Registers = 8;   // No of registers in the algorithm
    localparam No_Tests     = 10;  // no of test cases

    reg [No_Registers - 1:0] DATA_input       [0:No_Tests - 1];
    reg [No_Registers - 1:0] Expected_Out_CRC [0:No_Tests - 1];

    //-------------------------------------------------------------------------
    // Signals
    //-------------------------------------------------------------------------
    reg  DATA_TB, ACTIVE_TB, CLK_TB, RST_TB;
    wire CRC_TB, Valid_TB;

    integer test_num = 0;
    integer passed   = 0;
    integer failed   = 0;

    //-------------------------------------------------------------------------
    // DUT Instantiation
    //-------------------------------------------------------------------------
    CRC DUT_CRC (
        .DATA(DATA_TB), .ACTIVE(ACTIVE_TB),
        .CLK(CLK_TB), .RST(RST_TB),
        .CRC(CRC_TB), .Valid(Valid_TB)
    );

    //-------------------------------------------------------------------------
    // Clock Generation: 10 MHz (100 ns period)
    //-------------------------------------------------------------------------
    initial begin
        CLK_TB = 0;
        forever #(CLK_PERIOD / 2) CLK_TB = ~CLK_TB;
    end

    //-------------------------------------------------------------------------
    // Timeout Watchdog
    //-------------------------------------------------------------------------
    initial begin
        #100000;
        $display("[TIMEOUT] Simulation exceeded limit. Terminating.");
        $finish;
    end

    //-------------------------------------------------------------------------
    // Tasks
    //-------------------------------------------------------------------------
    task do_reset;
        begin
            RST_TB    = 1'b0;
            ACTIVE_TB = 1'b0;
            DATA_TB   = 1'b0;
            @(negedge CLK_TB);
            @(negedge CLK_TB);
            RST_TB = 1'b1;
            @(negedge CLK_TB);
        end
    endtask

    task drive_byte;
        input [No_Registers-1:0] byte_in;
        integer i;
        begin
            ACTIVE_TB = 1'b1;
            for (i = 0; i < No_Registers; i = i + 1) begin
                DATA_TB = byte_in[i];      // LSB first
                @(negedge CLK_TB);
            end
            ACTIVE_TB = 1'b0;
        end
    endtask

    task capture_and_check;
        input [No_Registers-1:0] expected;
        input integer idx;
        reg   [No_Registers-1:0] received;
        integer i;
        begin
            @(posedge Valid_TB);
            for (i = 0; i < No_Registers; i = i + 1) begin
                @(negedge CLK_TB);
                received[i] = CRC_TB;      // R0 first -> LSB, R7 last -> MSB
            end

            if (received === expected) begin
                $display("Test %0d PASSED  (expected=%h, got=%h)", idx, expected, received);
                passed = passed + 1;
            end else begin
                $display("Test %0d FAILED  (expected=%h, got=%h)", idx, expected, received);
                failed = failed + 1;
            end
        end
    endtask

    //-------------------------------------------------------------------------
    // Main stimulus
    //-------------------------------------------------------------------------
    initial begin
        $dumpfile("CRC_DUMP.vcd");
        $dumpvars;

        $readmemh("DATA_h.txt", DATA_input);
        $readmemh("Expec_Out_h.txt", Expected_Out_CRC);

        for (test_num = 0; test_num < No_Tests; test_num = test_num + 1) begin
            do_reset;
            drive_byte(DATA_input[test_num]);
            capture_and_check(Expected_Out_CRC[test_num], test_num);
        end

        $display("---------------------------------------");
        $display("TOTAL: %0d passed, %0d failed out of %0d", passed, failed, No_Tests);
        $display("---------------------------------------");
        #(CLK_PERIOD);
        $finish;
    end

endmodule //CRC_TB

Assignments/Verilog Assignments/Assignment 5/5.0/CRC_DUMP.vcd
$date
	Mon Jul 27 17:34:57 2026
$end
$version
	ModelSim Version 2020.1
$end
$timescale
	1ps
$end

$scope module CRC_TB $end
$var parameter 32 ! CLK_PERIOD $end
$var parameter 32 " No_Registers $end
$var parameter 32 # No_Tests $end
$var reg 1 $ DATA_TB $end
$var reg 1 % ACTIVE_TB $end
$var reg 1 & CLK_TB $end
$var reg 1 ' RST_TB $end
$var wire 1 ( CRC_TB $end
$var wire 1 ) Valid_TB $end
$var integer 32 * test_num $end
$var integer 32 + passed $end
$var integer 32 , failed $end

$scope task do_reset $end
$upscope $end

$scope task drive_byte $end
$var reg 8 - byte_in [7:0] $end
$var integer 32 . i $end
$upscope $end

$scope task capture_and_check $end
$var reg 8 / expected [7:0] $end
$var integer 32 0 idx $end
$var reg 8 1 received [7:0] $end
$var integer 32 2 i $end
$upscope $end

$scope module DUT_CRC $end
$var parameter 4 3 No_Registers $end
$var parameter 8 4 SEED $end
$var parameter 8 5 XOR_Bits $end
$var wire 1 6 DATA $end
$var wire 1 7 ACTIVE $end
$var wire 1 8 CLK $end
$var wire 1 9 RST $end
$var reg 1 : CRC $end
$var reg 1 ; Valid $end
$var reg 8 < LFSR [7:0] $end
$var reg 4 = Counter [3:0] $end
$var integer 32 > i $end
$var wire 1 ? DATA_XOR_R0_W1 $end
$var wire 1 @ Counter_Max $end
$upscope $end
$upscope $end
$enddefinitions $end
#0
$dumpvars
0$
0%
0&
0'
x:
0;
b11011000 <
b1000 =
bx -
bx /
bx 1
b1100100 !
b1000 "
b1010 #
b1000 3
b11011000 4
b1000100 5
b0 *
b0 +
b0 ,
bx >
bx .
bx 0
bx 2
x(
0)
0?
1@
09
08
07
06
$end
#50000
1&
18
#100000
0&
08
#150000
1&
18
#200000
0&
08
1'
19
#250000
1&
18
0:
0(
#300000
0&
08
b10010011 -
1%
b0 .
1$
17
16
1?
#350000
1&
18
b0 >
b1 >
b10 >
b11 >
b100 >
b101 >
b110 >
b111 >
b11001000 <
b11101000 <
b10101000 <
b0 =
0@
#400000
0&
08
b1 .
#450000
1&
18
b0 >
b1 >
b10 >
b11 >
b100 >
b101 >
b110 >
b111 >
b10100000 <
b10110000 <
b10010000 <
#500000
0&
08
b10 .
0$
06
0?
#550000
1&
18
b0 >
b1 >
b10 >
b11 >
b100 >
b101 >
b110 >
b111 >
b10000 <
b11000 <
b1000 <
b1001000 <
#600000
0&
08
b11 .
#650000
1&
18
b0 >
b1 >
b10 >
b11 >
b100 >
b101 >
b110 >
b111 >
b1001100 <
b1000100 <
b1100100 <
b100100 <
#700000
0&
08
b100 .
1$
16
1?
#750000
1&
18
b0 >
b1 >
b10 >
b11 >
b100 >
b101 >
b110 >
b111 >
b10100100 <
b10100110 <
b10110110 <
b10010110 <
b11010110 <
#800000
0&
08
b101 .
0$
06
0?
#850000
1&
18
b0 >
b1 >
b10 >
b11 >
b100 >
b101 >
b110 >
b111 >
b1010110 <
b1010111 <
b1010011 <
b1011011 <
b1001011 <
b1101011 <
1?
#900000
0&
08
b110 .
#950000
1&
18
b0 >
b1 >
b10 >
b11 >
b100 >
b101 >
b110 >
b111 >
b11101011 <
b11101001 <
b11100001 <
b11110001 <
#1000000
0&
08
b111 .
1$
16
0?
#1050000
1&
18
b0 >
b1 >
b10 >
b11 >
b100 >
b101 >
b110 >
b111 >
b1110001 <
b1110000 <
b1111000 <
1?
#1100000
0&
08
b1000 .
0%
b1111000 /
b0 0
07
#1150000
1&
18
b0 >
b1 >
b10 >
b11 >
b100 >
b101 >
b110 >
b111 >
1;
b1111100 <
b111100 <
b1 =
1)
b0 2
#1200000
0&
08
bx0 1
b1 2
#1250000
1&
18
b0 >
b1 >
b10 >
b11 >
b100 >
b101 >
b110 >
b111 >
b111110 <
b11110 <
b10 =
#1300000
0&
08
bx00 1
b10 2
#1350000
1&
18
b0 >
b1 >
b10 >
b11 >
b100 >
b101 >
b110 >
b111 >
b11111 <
b1111 <
b11 =
0?
#1400000
0&
08
bx000 1
b11 2
#1450000
1&
18
b0 >
b1 >
b10 >
b11 >
b100 >
b101 >
b110 >
b111 >
1:
b111 <
b100 =
1(
#1500000
0&
08
bx1000 1
b100 2
#1550000
1&
18
b0 >
b1 >
b10 >
b11 >
b100 >
b101 >
b110 >
b111 >
b11 <
b101 =
#1600000
0&
08
bx11000 1
b101 2
#1650000
1&
18
b0 >
b1 >
b10 >
b11 >
b100 >
b101 >
b110 >
b111 >
b1 <
b110 =
#1700000
0&
08
bx111000 1
b110 2
#1750000
1&
18
b0 >
b1 >
b10 >
b11 >
b100 >
b101 >
b110 >
b111 >
b0 <
b111 =
1?
#1800000
0&
08
bx1111000 1
b111 2
#1850000
1&
18
b0 >
b1 >
b10 >
b11 >
b100 >
b101 >
b110 >
b111 >
0:
b1000 =
0(
1@
#1900000
0&
08
b1111000 1
b1000 2
b1 +
b1 *
0'
0$
06
0?
09
b11011000 <
0;
0)
#1950000
1&
18
#2000000
0&
08
#2050000
1&
18
#2100000
0&
08
1'
19
#2150000
1&
18
#2200000
0&
08
b1110010 -
1%
b0 .
17
#2250000
1&
18
b0 >
b1 >
b10 >
b11 >
b100 >
b101 >
b110 >
b111 >
b1011000 <
b1011100 <
b1001100 <
b1101100 <
b0 =
0@
#2300000
0&
08
b1 .
1$
16
1?
#2350000
1&
18
b0 >
b1 >
b10 >
b11 >
b100 >
b101 >
b110 >
b111 >
b11101100 <
b11101110 <
b11101010 <
b11100010 <
b11110010 <
#2400000
0&
08
b10 .
0$
06
0?
#2450000
1&
18
b0 >
b1 >
b10 >
b11 >
b100 >
b101 >
b110 >
b111 >
b1110010 <
b1110011 <
b1110001 <
b1111001 <
1?
#2500000
0&
08
b11 .
#2550000
1&
18
b0 >
b1 >
b10 >
b11 >
b100 >
b101 >
b110 >
b111 >
b11111001 <
b11111000 <
0?
#2600000
0&
08
b100 .
1$
16
1?
#2650000
1&
18
b0 >
b1 >
b10 >
b11 >
b100 >
b101 >
b110 >
b111 >
b10111000 <
#2700000
0&
08
b101 .
#2750000
1&
18
b0 >
b1 >
b10 >
b11 >
b100 >
b101 >
b110 >
b111 >
b10011000 <
#2800000
0&
08
b110 .
#2850000
1&
18
b0 >
b1 >
b10 >
b11 >
b100 >
b101 >
b110 >
b111 >
b10001000 <
#2900000
0&
08
b111 .
0$
06
0?
#2950000
1&
18
b0 >
b1 >
b10 >
b11 >
b100 >
b101 >
b110 >
b111 >
b1000 <
b1100 <
b100 <
b1000100 <
#3000000
0&
08
b1000 .
0%
b1000100 /
b1 0
07
#3050000
1&
18
b0 >
b1 >
b10 >
b11 >
b100 >
b101 >
b110 >
b111 >
1;
b1000110 <
b1000010 <
b1100010 <
b100010 <
b1 =
1)
b0 2
#3100000
0&
08
b1 2
#3150000
1&
18
b0 >
b1 >
b10 >
b11 >
b100 >
b101 >
b110 >
b111 >
b100011 <
b100001 <
b110001 <
b10001 <
b10 =
1?
#3200000
0&
08
b10 2
#3250000
1&
18
b0 >
b1 >
b10 >
b11 >
b100 >
b101 >
b110 >
b111 >
1:
b10000 <
b11000 <
b1000 <
b11 =
0?
1(
#3300000
0&
08
b1111100 1
b11 2
#3350000
1&
18
b0 >
b1 >
b10 >
b11 >
b100 >
b101 >
b110 >
b111 >
0:
b1100 <
b100 <
b100 =
0(
#3400000
0&
08
b1110100 1
b100 2
#3450000
1&
18
b0 >
b1 >
b10 >
b11 >
b100 >
b101 >
b110 >
b111 >
b110 <
b10 <
b101 =
#3500000
0&
08
b1100100 1
b101 2
#3550000
1&
18
b0 >
b1 >
b10 >
b11 >
b100 >
b101 >
b110 >
b111 >
b11 <
b1 <
b110 =
1?
#3600000
0&
08
b1000100 1
b110 2
#3650000
1&
18
b0 >
b1 >
b10 >
b11 >
b100 >
b101 >
b110 >
b111 >
1:
b0 <
b111 =
0?
1(
#3700000
0&
08
b111 2
#3750000
1&
18
b0 >
b1 >
b10 >
b11 >
b100 >
b101 >
b110 >
b111 >
0:
b1000 =
0(
1@
#3800000
0&
08
b1000 2
b10 +
b10 *
0'
09
b11011000 <
0;
0)
#3850000
1&
18
#3900000
0&
08
#3950000
1&
18
#4000000
0&
08
1'
19
#4050000
1&
18
#4100000
0&
08
b110110 -
1%
b0 .
17
#4150000
1&
18
b0 >
b1 >
b10 >
b11 >
b100 >
b101 >
b110 >
b111 >
b1011000 <
b1011100 <
b1001100 <
b1101100 <
b0 =
0@
#4200000
0&
08
b1 .
1$
16
1?
#4250000
1&
18
b0 >
b1 >
b10 >
b11 >
b100 >
b101 >
b110 >
b111 >
b11101100 <
b11101110 <
b11101010 <
b11100010 <
b11110010 <
#4300000
0&
08
b10 .
#4350000
1&
18
b0 >
b1 >
b10 >
b11 >
b100 >
b101 >
b110 >
b111 >
b11110011 <
b11110001 <
b11110101 <
b11111101 <
b10111101 <
0?
#4400000
0&
08
b11 .
0$
06
1?
#4450000
1&
18
b0 >
b1 >
b10 >
b11 >
b100 >
b101 >
b110 >
b111 >
b10111100 <
b10111110 <
b10111010 <
b10011010 <
0?
#4500000
0&
08
b100 .
1$
16
1?
#4550000
1&
18
b0 >
b1 >
b10 >
b11 >
b100 >
b101 >
b110 >
b111 >
b10011011 <
b10011001 <
b10001001 <
0?
#4600000
0&
08
b101 .
#4650000
1&
18
b0 >
b1 >
b10 >
b11 >
b100 >
b101 >
b110 >
b111 >
b1001 <
b1000 <
b1100 <
b100 <
b1000100 <
1?
#4700000
0&
08
b110 .
0$
06
0?
#4750000
1&
18
b0 >
b1 >
b10 >
b11 >
b100 >
b101 >
b110 >
b111 >
b1000110 <
b1000010 <
b1100010 <
b100010 <
#4800000
0&
08
b111 .
#4850000
1&
18
b0 >
b1 >
b10 >
b11 >
b100 >
b101 >
b110 >
b111 >
b100011 <
b100001 <
b110001 <
b10001 <
1?
#4900000
0&
08
b1000 .
0%
b10001 /
b10 0
07
#4950000
1&
18
b0 >
b1 >
b10 >
b11 >
b100 >
b101 >
b110 >
b111 >
1;
1:
b10000 <
b11000 <
b1000 <
b1 =
0?
1(
1)
b0 2
#5000000
0&
08
b1000101 1
b1 2
#5050000
1&
18
b0 >
b1 >
b10 >
b11 >
b100 >
b101 >
b110 >
b111 >
0:
b1100 <
b100 <
b10 =
0(
#5100000
0&
08
b10 2
#5150000
1&
18
b0 >
b1 >
b10 >
b11 >
b100 >
b101 >
b110 >
b111 >
b110 <
b10 <
b11 =
#5200000
0&
08
b1000001 1
b11 2
#5250000
1&
18
b0 >
b1 >
b10 >
b11 >
b100 >
b101 >
b110 >
b111 >
b11 <
b1 <
b100 =
1?
#5300000
0&
08
b100 2
#5350000
1&
18
b0 >
b1 >
b10 >
b11 >
b100 >
b101 >
b110 >
b111 >
1:
b0 <
b101 =
0?
1(
#5400000
0&
08
b1010001 1
b101 2
#5450000
1&
18
b0 >
b1 >
b10 >
b11 >
b100 >
b101 >
b110 >
b111 >
0:
b110 =
0(
#5500000
0&
08
b110 2
#5550000
1&
18
b0 >
b1 >
b10 >
b11 >
b100 >
b101 >
b110 >
b111 >
b111 =
#5600000
0&
08
b10001 1
b111 2
#5650000
1&
18
b0 >
b1 >
b10 >
b11 >
b100 >
b101 >
b110 >
b111 >
b1000 =
1@
#5700000
0&
08
b1000 2
b11 +
b11 *
0'
09
b11011000 <
0;
0)
#5750000
1&
18
#5800000
0&
08
#5850000
1&
18
#5900000
0&
08
1'
19
#5950000
1&
18
#6000000
0&
08
b11011 -
1%
b0 .
1$
17
16
1?
#6050000
1&
18
b0 >
b1 >
b10 >
b11 >
b100 >
b101 >
b110 >
b111 >
b11001000 <
b11101000 <
b10101000 <
b0 =
0@
#6100000
0&
08
b1 .
#6150000
1&
18
b0 >
b1 >
b10 >
b11 >
b100 >
b101 >
b110 >
b111 >
b10100000 <
b10110000 <
b10010000 <
#6200000
0&
08
b10 .
0$
06
0?
#6250000
1&
18
b0 >
b1 >
b10 >
b11 >
b100 >
b101 >
b110 >
b111 >
b10000 <
b11000 <
b1000 <
b1001000 <
#6300000
0&
08
b11 .
1$
16
1?
#6350000
1&
18
b0 >
b1 >
b10 >
b11 >
b100 >
b101 >
b110 >
b111 >
b11001000 <
b11000000 <
b11100000 <
#6400000
0&
08
b100 .
#6450000
1&
18
b0 >
b1 >
b10 >
b11 >
b100 >
b101 >
b110 >
b111 >
b11100100 <
b11110100 <
b10110100 <
#6500000
0&
08
b101 .
0$
06
0?
#6550000
1&
18
b0 >
b1 >
b10 >
b11 >
b100 >
b101 >
b110 >
b111 >
b110100 <
b110110 <
b110010 <
b111010 <
b11010 <
b1011010 <
#6600000
0&
08
b110 .
#6650000
1&
18
b0 >
b1 >
b10 >
b11 >
b100 >
b101 >
b110 >
b111 >
b1011011 <
b1011001 <
b1011101 <
b1001101 <
b1101101 <
b101101 <
1?
#6700000
0&
08
b111 .
#6750000
1&
18
b0 >
b1 >
b10 >
b11 >
b100 >
b101 >
b110 >
b111 >
b10101101 <
b10101100 <
b10101110 <
b10101010 <
b10100010 <
b10110010 <
b10010010 <
b11010010 <
0?
#6800000
0&
08
b1000 .
0%
b11010010 /
b11 0
07
#6850000
1&
18
b0 >
b1 >
b10 >
b11 >
b100 >
b101 >
b110 >
b111 >
1;
b1010010 <
b1010011 <
b1010001 <
b1011001 <
b1001001 <
b1101001 <
b1 =
1?
1)
b0 2
#6900000
0&
08
b10000 1
b1 2
#6950000
1&
18
b0 >
b1 >
b10 >
b11 >
b100 >
b101 >
b110 >
b111 >
1:
b1101000 <
b1101100 <
b1100100 <
b1110100 <
b110100 <
b10 =
0?
1(
#7000000
0&
08
b10010 1
b10 2
#7050000
1&
18
b0 >
b1 >
b10 >
b11 >
b100 >
b101 >
b110 >
b111 >
0:
b110110 <
b110010 <
b111010 <
b11010 <
b11 =
0(
#7100000
0&
08
b11 2
#7150000
1&
18
b0 >
b1 >
b10 >
b11 >
b100 >
b101 >
b110 >
b111 >
b11011 <
b11001 <
b11101 <
b1101 <
b100 =
1?
#7200000
0&
08
b100 2
#7250000
1&
18
b0 >
b1 >
b10 >
b11 >
b100 >
b101 >
b110 >
b111 >
1:
b1100 <
b1110 <
b110 <
b101 =
0?
1(
#7300000
0&
08
b101 2
#7350000
1&
18
b0 >
b1 >
b10 >
b11 >
b100 >
b101 >
b110 >
b111 >
0:
b111 <
b11 <
b110 =
1?
0(
#7400000
0&
08
b110 2
#7450000
1&
18
b0 >
b1 >
b10 >
b11 >
b100 >
b101 >
b110 >
b111 >
1:
b1 <
b111 =
1(
#7500000
0&
08
b1010010 1
b111 2
#7550000
1&
18
b0 >
b1 >
b10 >
b11 >
b100 >
b101 >
b110 >
b111 >
b0 <
b1000 =
0?
1@
#7600000
0&
08
b11010010 1
b1000 2
b100 +
b100 *
0'
09
b11011000 <
0;
0)
#7650000
1&
18
#7700000
0&
08
#7750000
1&
18
#7800000
0&
08
1'
19
#7850000
1&
18
0:
0(
#7900000
0&
08
b10100110 -
1%
b0 .
17
#7950000
1&
18
b0 >
b1 >
b10 >
b11 >
b100 >
b101 >
b110 >
b111 >
b1011000 <
b1011100 <
b1001100 <
b1101100 <
b0 =
0@
#8000000
0&
08
b1 .
1$
16
1?
#8050000
1&
18
b0 >
b1 >
b10 >
b11 >
b100 >
b101 >
b110 >
b111 >
b11101100 <
b11101110 <
b11101010 <
b11100010 <
b11110010 <
#8100000
0&
08
b10 .
#8150000
1&
18
b0 >
b1 >
b10 >
b11 >
b100 >
b101 >
b110 >
b111 >
b11110011 <
b11110001 <
b11110101 <
b11111101 <
b10111101 <
0?
#8200000
0&
08
b11 .
0$
06
1?
#8250000
1&
18
b0 >
b1 >
b10 >
b11 >
b100 >
b101 >
b110 >
b111 >
b10111100 <
b10111110 <
b10111010 <
b10011010 <
0?
#8300000
0&
08
b100 .
#8350000
1&
18
b0 >
b1 >
b10 >
b11 >
b100 >
b101 >
b110 >
b111 >
b11010 <
b11011 <
b11001 <
b11101 <
b1101 <
b1001101 <
1?
#8400000
0&
08
b101 .
1$
16
0?
#8450000
1&
18
b0 >
b1 >
b10 >
b11 >
b100 >
b101 >
b110 >
b111 >
b1001100 <
b1001110 <
b1000110 <
b1100110 <
b100110 <
1?
#8500000
0&
08
b110 .
0$
06
0?
#8550000
1&
18
b0 >
b1 >
b10 >
b11 >
b100 >
b101 >
b110 >
b111 >
b100111 <
b100011 <
b110011 <
b10011 <
1?
#8600000
0&
08
b111 .
1$
16
0?
#8650000
1&
18
b0 >
b1 >
b10 >
b11 >
b100 >
b101 >
b110 >
b111 >
b10001 <
b11001 <
b1001 <
#8700000
0&
08
b1000 .
0%
b1001 /
b100 0
07
#8750000
1&
18
b0 >
b1 >
b10 >
b11 >
b100 >
b101 >
b110 >
b111 >
1;
1:
b1000 <
b1100 <
b100 <
b1 =
1?
1(
1)
b0 2
#8800000
0&
08
b11010011 1
b1 2
#8850000
1&
18
b0 >
b1 >
b10 >
b11 >
b100 >
b101 >
b110 >
b111 >
0:
b110 <
b10 <
b10 =
0(
#8900000
0&
08
b11010001 1
b10 2
#8950000
1&
18
b0 >
b1 >
b10 >
b11 >
b100 >
b101 >
b110 >
b111 >
b11 <
b1 <
b11 =
0?
#9000000
0&
08
b11 2
#9050000
1&
18
b0 >
b1 >
b10 >
b11 >
b100 >
b101 >
b110 >
b111 >
1:
b0 <
b100 =
1?
1(
#9100000
0&
08
b11011001 1
b100 2
#9150000
1&
18
b0 >
b1 >
b10 >
b11 >
b100 >
b101 >
b110 >
b111 >
0:
b101 =
0(
#9200000
0&
08
b11001001 1
b101 2
#9250000
1&
18
b0 >
b1 >
b10 >
b11 >
b100 >
b101 >
b110 >
b111 >
b110 =
#9300000
0&
08
b110 2
#9350000
1&
18
b0 >
b1 >
b10 >
b11 >
b100 >
b101 >
b110 >
b111 >
b111 =
#9400000
0&
08
b10001001 1
b111 2
#9450000
1&
18
b0 >
b1 >
b10 >
b11 >
b100 >
b101 >
b110 >
b111 >
b1000 =
1@
#9500000
0&
08
b1001 1
b1000 2
b101 +
b101 *
0'
0$
06
0?
09
b11011000 <
0;
0)
#9550000
1&
18
#9600000
0&
08
#9650000
1&
18
#9700000
0&
08
1'
19
#9750000
1&
18
#9800000
0&
08
b11000000 -
1%
b0 .
17
#9850000
1&
18
b0 >
b1 >
b10 >
b11 >
b100 >
b101 >
b110 >
b111 >
b1011000 <
b1011100 <
b1001100 <
b1101100 <
b0 =
0@
#9900000
0&
08
b1 .
#9950000
1&
18
b0 >
b1 >
b10 >
b11 >
b100 >
b101 >
b110 >
b111 >
b1101110 <
b1100110 <
b1110110 <
b110110 <
#10000000
0&
08
b10 .
#10050000
1&
18
b0 >
b1 >
b10 >
b11 >
b100 >
b101 >
b110 >
b111 >
b110111 <
b110011 <
b111011 <
b11011 <
1?
#10100000
0&
08
b11 .
#10150000
1&
18
b0 >
b1 >
b10 >
b11 >
b100 >
b101 >
b110 >
b111 >
b10011011 <
b10011001 <
b10001001 <
b11001001 <
#10200000
0&
08
b100 .
#10250000
1&
18
b0 >
b1 >
b10 >
b11 >
b100 >
b101 >
b110 >
b111 >
b11001000 <
b11000000 <
b11100000 <
b10100000 <
0?
#10300000
0&
08
b101 .
#10350000
1&
18
b0 >
b1 >
b10 >
b11 >
b100 >
b101 >
b110 >
b111 >
b100000 <
b110000 <
b10000 <
b1010000 <
#10400000
0&
08
b110 .
1$
16
1?
#10450000
1&
18
b0 >
b1 >
b10 >
b11 >
b100 >
b101 >
b110 >
b111 >
b11010000 <
b11010100 <
b11011100 <
b11001100 <
b11101100 <
#10500000
0&
08
b111 .
#10550000
1&
18
b0 >
b1 >
b10 >
b11 >
b100 >
b101 >
b110 >
b111 >
b11101110 <
b11101010 <
b11100010 <
b11110010 <
b10110010 <
#10600000
0&
08
b1000 .
0%
b10110010 /
b101 0
07
#10650000
1&
18
b0 >
b1 >
b10 >
b11 >
b100 >
b101 >
b110 >
b111 >
1;
b110010 <
b110011 <
b110001 <
b111001 <
b11001 <
b1011001 <
b1 =
0?
1)
b0 2
#10700000
0&
08
b1000 1
b1 2
#10750000
1&
18
b0 >
b1 >
b10 >
b11 >
b100 >
b101 >
b110 >
b111 >
1:
b1011000 <
b1011100 <
b1001100 <
b1101100 <
b101100 <
b10 =
1?
1(
#10800000
0&
08
b1010 1
b10 2
#10850000
1&
18
b0 >
b1 >
b10 >
b11 >
b100 >
b101 >
b110 >
b111 >
0:
b101110 <
b100110 <
b110110 <
b10110 <
b11 =
0(
#10900000
0&
08
b11 2
#10950000
1&
18
b0 >
b1 >
b10 >
b11 >
b100 >
b101 >
b110 >
b111 >
b10111 <
b10011 <
b11011 <
b1011 <
b100 =
0?
#11000000
0&
08
b10 1
b100 2
#11050000
1&
18
b0 >
b1 >
b10 >
b11 >
b100 >
b101 >
b110 >
b111 >
1:
b1001 <
b1101 <
b101 <
b101 =
1(
#11100000
0&
08
b10010 1
b101 2
#11150000
1&
18
b0 >
b1 >
b10 >
b11 >
b100 >
b101 >
b110 >
b111 >
b100 <
b110 <
b10 <
b110 =
1?
#11200000
0&
08
b110010 1
b110 2
#11250000
1&
18
b0 >
b1 >
b10 >
b11 >
b100 >
b101 >
b110 >
b111 >
0:
b11 <
b1 <
b111 =
0?
0(
#11300000
0&
08
b111 2
#11350000
1&
18
b0 >
b1 >
b10 >
b11 >
b100 >
b101 >
b110 >
b111 >
1:
b0 <
b1000 =
1?
1(
1@
#11400000
0&
08
b10110010 1
b1000 2
b110 +
b110 *
0'
0$
06
0?
09
b11011000 <
0;
0)
#11450000
1&
18
#11500000
0&
08
#11550000
1&
18
#11600000
0&
08
1'
19
#11650000
1&
18
0:
0(
#11700000
0&
08
b1010101 -
1%
b0 .
1$
17
16
1?
#11750000
1&
18
b0 >
b1 >
b10 >
b11 >
b100 >
b101 >
b110 >
b111 >
b11001000 <
b11101000 <
b10101000 <
b0 =
0@
#11800000
0&
08
b1 .
0$
06
0?
#11850000
1&
18
b0 >
b1 >
b10 >
b11 >
b100 >
b101 >
b110 >
b111 >
b101000 <
b101100 <
b100100 <
b110100 <
b10100 <
b1010100 <
#11900000
0&
08
b10 .
1$
16
1?
#11950000
1&
18
b0 >
b1 >
b10 >
b11 >
b100 >
b101 >
b110 >
b111 >
b11010100 <
b11010110 <
b11011110 <
b11001110 <
b11101110 <
#12000000
0&
08
b11 .
0$
06
0?
#12050000
1&
18
b0 >
b1 >
b10 >
b11 >
b100 >
b101 >
b110 >
b111 >
b1101110 <
b1101111 <
b1100111 <
b1110111 <
1?
#12100000
0&
08
b100 .
1$
16
0?
#12150000
1&
18
b0 >
b1 >
b10 >
b11 >
b100 >
b101 >
b110 >
b111 >
b1110011 <
b1111011 <
b111011 <
#12200000
0&
08
b101 .
0$
06
1?
#12250000
1&
18
b0 >
b1 >
b10 >
b11 >
b100 >
b101 >
b110 >
b111 >
b10111011 <
b10111001 <
b10011001 <
b11011001 <
#12300000
0&
08
b110 .
1$
16
0?
#12350000
1&
18
b0 >
b1 >
b10 >
b11 >
b100 >
b101 >
b110 >
b111 >
b1011001 <
b1011000 <
b1011100 <
b1001100 <
b1101100 <
1?
#12400000
0&
08
b111 .
0$
06
0?
#12450000
1&
18
b0 >
b1 >
b10 >
b11 >
b100 >
b101 >
b110 >
b111 >
b1101110 <
b1100110 <
b1110110 <
b110110 <
#12500000
0&
08
b1000 .
0%
b110110 /
b110 0
07
#12550000
1&
18
b0 >
b1 >
b10 >
b11 >
b100 >
b101 >
b110 >
b111 >
1;
b110111 <
b110011 <
b111011 <
b11011 <
b1 =
1?
1)
b0 2
#12600000
0&
08
b1 2
#12650000
1&
18
b0 >
b1 >
b10 >
b11 >
b100 >
b101 >
b110 >
b111 >
1:
b11001 <
b11101 <
b1101 <
b10 =
1(
#12700000
0&
08
b10 2
#12750000
1&
18
b0 >
b1 >
b10 >
b11 >
b100 >
b101 >
b110 >
b111 >
b1100 <
b1110 <
b110 <
b11 =
0?
#12800000
0&
08
b10110110 1
b11 2
#12850000
1&
18
b0 >
b1 >
b10 >
b11 >
b100 >
b101 >
b110 >
b111 >
0:
b111 <
b11 <
b100 =
1?
0(
#12900000
0&
08
b100 2
#12950000
1&
18
b0 >
b1 >
b10 >
b11 >
b100 >
b101 >
b110 >
b111 >
1:
b1 <
b101 =
1(
#13000000
0&
08
b101 2
#13050000
1&
18
b0 >
b1 >
b10 >
b11 >
b100 >
b101 >
b110 >
b111 >
b0 <
b110 =
0?
#13100000
0&
08
b110 2
#13150000
1&
18
b0 >
b1 >
b10 >
b11 >
b100 >
b101 >
b110 >
b111 >
0:
b111 =
0(
#13200000
0&
08
b111 2
