Labs/Lab 3/3.0/counter_tb.v
`timescale 1ns/1ns
module Counter(
    input [3:0] IN,
    input latch,dec,clk,
    output reg [3:0] counter,
    output zero
);
    assign zero = (counter == 0);
    always @(posedge clk) begin
        if(latch)
            begin
                counter <= IN;
            end
        else if (dec && !zero)
            begin
                counter <= counter - 1;
            end
        else
            counter <= counter;
    end
endmodule


module counter_TB;
    reg [3:0] IN_TB;
    reg latch_TB,dec_TB,clk_TB;
    wire [3:0] counter_TB;
    wire zero_TB;
    Counter DUT_DN_Counter (
        .counter(counter_TB),
        .IN(IN_TB),
        .latch(latch_TB),
        .zero(zero_TB),
        .clk(clk_TB),
        .dec(dec_TB)
    );
    initial begin
        clk_TB = 0;
        forever begin
            #5 clk_TB = ~clk_TB;
        end
    end
    initial begin
        $dumpfile("Counter_TB.vcd");
        $dumpvars;
    end
    initial begin
        $monitor("At t = %0t,Counter = %b,Zero Flag = %b",$time,counter_TB,zero_TB);
    end
    initial begin
        #160 $finish;
    end
    initial fork
        #0 {latch_TB,dec_TB,IN_TB} = 6'b100111;
        #15 {latch_TB,dec_TB} = 2'b01;
        #30 {latch_TB,dec_TB} = 2'b00;
        #50 {latch_TB,dec_TB,IN_TB} = 6'b100011;
        #60 {latch_TB,dec_TB} = 2'b01;
    join
endmodule

Labs/Lab 3/3.0/Counter_TB.vcd
$date
	Fri Jul 10 10:41:38 2026
$end
$version
	Icarus Verilog
$end
$timescale
	1ns
$end
$scope module counter_TB $end
$var wire 1 ! zero_TB $end
$var wire 4 " counter_TB [3:0] $end
$var reg 4 # IN_TB [3:0] $end
$var reg 1 $ clk_TB $end
$var reg 1 % dec_TB $end
$var reg 1 & latch_TB $end
$scope module DUT_DN_Counter $end
$var wire 4 ' IN [3:0] $end
$var wire 1 $ clk $end
$var wire 1 % dec $end
$var wire 1 & latch $end
$var wire 1 ! zero $end
$var reg 4 ( counter [3:0] $end
$upscope $end
$upscope $end
$enddefinitions $end
$comment Show the parameter values. $end
$dumpall
$end
#0
$dumpvars
bx (
b111 '
1&
0%
0$
b111 #
bx "
x!
$end
#5
0!
b111 "
b111 (
1$
#10
0$
#15
b110 "
b110 (
1$
0&
1%
#20
0$
#25
b101 "
b101 (
1$
#30
0$
0%
#35
1$
#40
0$
#45
1$
#50
0$
1&
b11 #
b11 '
#55
b11 "
b11 (
1$
#60
0$
0&
1%
#65
b10 "
b10 (
1$
#70
0$
#75
b1 "
b1 (
1$
#80
0$
#85
1!
b0 "
b0 (
1$
