Assignments/Verilog Assignments/Assignment 4/4.1/Register_File.v
module Register_File (
    input [15:0] WrData,
    input [2:0] Address,
    input WrEn,RdEn,
    input CLK,RST,
    output reg [15:0] RdData
);
    reg [15:0] Register_File_MEM [0:7];
    always @(posedge CLK or negedge RST) begin
        if (!RST) begin
            Register_File_MEM[0] <= 0;
            Register_File_MEM[1] <= 0;
            Register_File_MEM[2] <= 0;
            Register_File_MEM[3] <= 0;
            Register_File_MEM[4] <= 0;
            Register_File_MEM[5] <= 0;
            Register_File_MEM[6] <= 0;
            Register_File_MEM[7] <= 0;
        end
        else if (WrEn) begin
            Register_File_MEM[Address] <= WrData;
        end
        else if (RdEn) begin
            RdData <= Register_File_MEM[Address];
        end
    end
endmodule //Register_File

Assignments/Verilog Assignments/Assignment 4/4.1/Register_File_tb.v
`timescale 1ns/1ps

module Register_File_tb;

    // Testbench signals
    reg [15:0] WrData;
    reg [2:0] Address;
    reg WrEn, RdEn;
    reg CLK, RST;
    wire [15:0] RdData;

    // Instantiate the Unit Under Test (UUT)
    Register_File uut (
        .WrData(WrData),
        .Address(Address),
        .WrEn(WrEn),
        .RdEn(RdEn),
        .CLK(CLK),
        .RST(RST),
        .RdData(RdData)
    );

    // Clock generation: 10ns period (100MHz)
    initial begin
        CLK = 0;
        forever #5 CLK = ~CLK;
    end

    // Test scenarios
    initial begin
        $display("========================================");
        $display("     Register File Testbench Started");
        $display("========================================");

        // Initialize inputs
        WrData = 16'h0000;
        Address = 3'b000;
        WrEn = 0;
        RdEn = 0;

        //--------------------------------------------------
        // Scenario 1: Reset Test
        //--------------------------------------------------
        $display("\n--- Scenario 1: Asynchronous Reset ---");
        RST = 0;  // Assert reset (active low)
        #20;
        RST = 1;  // Deassert reset
        #10;
        $display("Reset completed. All registers cleared.");

        //--------------------------------------------------
        // Scenario 2: Write to Register 0
        //--------------------------------------------------
        $display("\n--- Scenario 2: Write to Register 0 ---");
        @(posedge CLK);
        Address = 3'b000;      // Register 0
        WrData = 16'hABCD;     // Data to write
        WrEn = 1;              // Enable write
        RdEn = 0;
        
        @(posedge CLK);
        WrEn = 0;              // Disable write
        #10;
        $display("Wrote 0x%h to Register 0", 16'hABCD);

        //--------------------------------------------------
        // Scenario 3: Write to Register 3
        //--------------------------------------------------
        $display("\n--- Scenario 3: Write to Register 3 ---");
        @(posedge CLK);
        Address = 3'b011;      // Register 3
        WrData = 16'h1234;     // Data to write
        WrEn = 1;
        RdEn = 0;
        
        @(posedge CLK);
        WrEn = 0;
        #10;
        $display("Wrote 0x%h to Register 3", 16'h1234);

        //--------------------------------------------------
        // Scenario 4: Read from Register 0
        //--------------------------------------------------
        $display("\n--- Scenario 4: Read from Register 0 ---");
        @(posedge CLK);
        Address = 3'b000;      // Register 0
        WrEn = 0;
        RdEn = 1;              // Enable read
        
        @(posedge CLK);
        #1;  // Small delay to see output
        $display("Read from Register 0: 0x%h (Expected: 0xABCD)", RdData);
        RdEn = 0;

        //--------------------------------------------------
        // Scenario 5: Read from Register 3
        //--------------------------------------------------
        $display("\n--- Scenario 5: Read from Register 3 ---");
        @(posedge CLK);
        Address = 3'b011;      // Register 3
        WrEn = 0;
        RdEn = 1;              // Enable read
        
        @(posedge CLK);
        #1;
        $display("Read from Register 3: 0x%h (Expected: 0x1234)", RdData);
        RdEn = 0;

        //--------------------------------------------------
        // Scenario 6: Verify Reset clears registers
        //--------------------------------------------------
        $display("\n--- Scenario 6: Verify Reset Clears All ---");
        RST = 0;  // Assert reset
        #15;
        RST = 1;  // Deassert
        
        // Try to read register 0 after reset
        @(posedge CLK);
        Address = 3'b000;
        RdEn = 1;
        
        @(posedge CLK);
        #1;
        $display("Read Register 0 after reset: 0x%h (Expected: 0x0000)", RdData);
        RdEn = 0;

        //--------------------------------------------------
        // End Simulation
        //--------------------------------------------------
        #20;
        $display("\n========================================");
        $display("     Register File Testbench Finished");
        $display("========================================");
        $finish;
    end

    // Monitor changes
    initial begin
        $monitor("Time=%0t | RST=%b | WrEn=%b | RdEn=%b | Addr=%d | WrData=0x%h | RdData=0x%h",
                 $time, RST, WrEn, RdEn, Address, WrData, RdData);
    end

    // Generate VCD file for waveform viewing
    initial begin
        $dumpfile("register_file.vcd");
        $dumpvars(0, Register_File_tb);
    end

endmodule

Assignments/Verilog Assignments/Assignment 4/4.1/register_file.vcd
$date
	Mon Jul 20 19:26:26 2026
$end
$version
	ModelSim Version 2020.1
$end
$timescale
	1ps
$end

$scope module Register_File_tb $end
$var reg 16 ! WrData [15:0] $end
$var reg 3 " Address [2:0] $end
$var reg 1 # WrEn $end
$var reg 1 $ RdEn $end
$var reg 1 % CLK $end
$var reg 1 & RST $end
$var wire 1 ' RdData [15] $end
$var wire 1 ( RdData [14] $end
$var wire 1 ) RdData [13] $end
$var wire 1 * RdData [12] $end
$var wire 1 + RdData [11] $end
$var wire 1 , RdData [10] $end
$var wire 1 - RdData [9] $end
$var wire 1 . RdData [8] $end
$var wire 1 / RdData [7] $end
$var wire 1 0 RdData [6] $end
$var wire 1 1 RdData [5] $end
$var wire 1 2 RdData [4] $end
$var wire 1 3 RdData [3] $end
$var wire 1 4 RdData [2] $end
$var wire 1 5 RdData [1] $end
$var wire 1 6 RdData [0] $end

$scope module uut $end
$var wire 1 7 WrData [15] $end
$var wire 1 8 WrData [14] $end
$var wire 1 9 WrData [13] $end
$var wire 1 : WrData [12] $end
$var wire 1 ; WrData [11] $end
$var wire 1 < WrData [10] $end
$var wire 1 = WrData [9] $end
$var wire 1 > WrData [8] $end
$var wire 1 ? WrData [7] $end
$var wire 1 @ WrData [6] $end
$var wire 1 A WrData [5] $end
$var wire 1 B WrData [4] $end
$var wire 1 C WrData [3] $end
$var wire 1 D WrData [2] $end
$var wire 1 E WrData [1] $end
$var wire 1 F WrData [0] $end
$var wire 1 G Address [2] $end
$var wire 1 H Address [1] $end
$var wire 1 I Address [0] $end
$var wire 1 J WrEn $end
$var wire 1 K RdEn $end
$var wire 1 L CLK $end
$var wire 1 M RST $end
$var reg 16 N RdData [15:0] $end
$upscope $end
$upscope $end
$enddefinitions $end
#0
$dumpvars
b0 !
b0 "
0#
0$
0%
0&
bx N
x6
x5
x4
x3
x2
x1
x0
x/
x.
x-
x,
x+
x*
x)
x(
x'
0M
0L
0K
0J
0I
0H
0G
0F
0E
0D
0C
0B
0A
0@
0?
0>
0=
0<
0;
0:
09
08
07
$end
#5000
1%
1L
#10000
0%
0L
#15000
1%
1L
#20000
1&
0%
1M
0L
#25000
1%
1L
#30000
0%
0L
#35000
1%
1L
b1010101111001101 !
1#
1F
1D
1C
1@
1?
1>
1=
1;
19
17
1J
#40000
0%
0L
#45000
1%
1L
0#
0J
#50000
0%
0L
#55000
1%
1L
b11 "
b1001000110100 !
1#
0F
0C
1B
1A
0@
0?
0>
0;
1:
09
07
1I
1H
1J
#60000
0%
0L
#65000
1%
1L
0#
0J
#70000
0%
0L
#75000
1%
1L
b0 "
1$
0I
0H
1K
#80000
0%
0L
#85000
1%
1L
b1010101111001101 N
16
05
14
13
02
01
10
1/
1.
1-
0,
1+
0*
1)
0(
1'
#86000
0$
0K
#90000
0%
0L
#95000
1%
1L
b11 "
1$
1I
1H
1K
#100000
0%
0L
#105000
1%
1L
b1001000110100 N
06
03
12
11
00
0/
0.
0+
1*
0)
0'
#106000
0$
0&
0K
0M
#110000
0%
0L
#115000
1%
1L
#120000
0%
0L
#121000
1&
1M
#125000
1%
1L
b0 "
1$
0I
0H
1K
#130000
0%
0L
#135000
1%
1L
b0 N
04
02
01
0-
0*
#136000
0$
0K
