Assignments/RST_SYNC/RST_SYNC.v
module RST_SYNC #(
    parameter NUM_STAGES = 2
)(
    input CLK,RST,
    output SYNC_RST
);
    reg [NUM_STAGES - 1:0] Synchronizer;
    always @(posedge CLK or negedge RST) begin
        if(!RST) begin
            Synchronizer <= 0;
        end
        else begin
            Synchronizer <= {1'b1,Synchronizer[NUM_STAGES - 1:1]};
        end
    end
    assign SYNC_RST = Synchronizer[0];
endmodule //RST_SYNC

Assignments/RST_SYNC/tb_RST_SYNC.v
`timescale 1ns/1ps

module tb_RST_SYNC;

    // ------------------------------------------------------------
    // Parameters
    // ------------------------------------------------------------
    parameter NUM_STAGES  = 2;
    parameter CLK_PERIOD  = 10;
    parameter NUM_RANDOM_ITER = 10;

    // ------------------------------------------------------------
    // DUT signals
    // ------------------------------------------------------------
    reg  CLK;
    reg  RST;
    wire SYNC_RST;

    integer errors = 0;
    integer i;

    time last_posedge_clk_time;
    time last_negedge_rst_time;

    // ------------------------------------------------------------
    // DUT instantiation
    // ------------------------------------------------------------
    RST_SYNC #(
        .NUM_STAGES(NUM_STAGES)
    ) DUT (
        .CLK      (CLK),
        .RST      (RST),
        .SYNC_RST (SYNC_RST)
    );

    // ------------------------------------------------------------
    // Clock generation
    // ------------------------------------------------------------
    initial CLK = 1'b0;
    always #(CLK_PERIOD/2) CLK = ~CLK;

    // ------------------------------------------------------------
    // Track reference edges for alignment checks
    // ------------------------------------------------------------
    always @(posedge CLK) last_posedge_clk_time <= $time;
    always @(negedge RST) last_negedge_rst_time <= $time;

    // ------------------------------------------------------------
    // Checker 1: SYNC_RST must fall the instant RST falls (async assert)
    // ------------------------------------------------------------
    always @(negedge SYNC_RST) begin
        if ($time !== last_negedge_rst_time) begin
            $display("[%0t] ERROR: SYNC_RST fell at a time not aligned with RST negedge (RST negedge was at %0t)",
                       $time, last_negedge_rst_time);
            errors = errors + 1;
        end else begin
            $display("[%0t] PASS: SYNC_RST asserted immediately/asynchronously with RST", $time);
        end
    end

    // ------------------------------------------------------------
    // Checker 2: SYNC_RST must only rise on a posedge CLK (sync de-assert)
    // ------------------------------------------------------------
    always @(posedge SYNC_RST) begin
        if ($time !== last_posedge_clk_time) begin
            $display("[%0t] ERROR: SYNC_RST rose at a time not aligned with a CLK posedge (last posedge was at %0t)",
                       $time, last_posedge_clk_time);
            errors = errors + 1;
        end else begin
            $display("[%0t] PASS: SYNC_RST de-asserted synchronously with CLK posedge", $time);
        end
    end

    // ------------------------------------------------------------
    // Task: apply an async reset pulse, de-assert at a non clock-aligned
    // time, then measure the de-assertion latency in clock edges
    // ------------------------------------------------------------
    task run_reset_pulse;
        input [31:0] assert_offset;   // async offset before asserting (ns)
        input [31:0] hold_time;       // how long to hold reset low (ns)
        integer cyc_count;
        begin
            #assert_offset;
            RST = 1'b0;
            $display("[%0t] RST asserted (async)", $time);

            #hold_time;
            if (SYNC_RST !== 1'b0) begin
                $display("[%0t] ERROR: SYNC_RST is not 0 while RST is held low", $time);
                errors = errors + 1;
            end

            RST = 1'b1;
            $display("[%0t] RST de-asserted (async, mid-cycle)", $time);

            cyc_count = 0;
            while (SYNC_RST !== 1'b1) begin
                @(posedge CLK);
                #1; // let the DUT's nonblocking update settle before sampling
                cyc_count = cyc_count + 1;
            end

            $display("[%0t] Measured de-assertion latency = %0d clock edge(s) (expected %0d)",
                       $time, cyc_count, NUM_STAGES);

            if (cyc_count !== NUM_STAGES) begin
                $display("[%0t] ERROR: Latency mismatch! Expected %0d, got %0d",
                           $time, NUM_STAGES, cyc_count);
                errors = errors + 1;
            end else begin
                $display("[%0t] PASS: Latency matches NUM_STAGES", $time);
            end
        end
    endtask

    // ------------------------------------------------------------
    // Stimulus
    // ------------------------------------------------------------
    initial begin
        $dumpfile("tb_RST_SYNC.vcd");
        $dumpvars(0, tb_RST_SYNC);

        $display("========================================================");
        $display(" RST_SYNC Testbench Start (NUM_STAGES = %0d)", NUM_STAGES);
        $display("========================================================");

        RST = 1'b1;
        #3; // start mid-cycle, not aligned to a clock edge

        // Directed test 1: simple reset pulse
        run_reset_pulse(4, 23);
        #(CLK_PERIOD*4);

        // Directed test 2: reset asserted again while chain is mid-fill
        run_reset_pulse(7, 3);   // very short hold, well inside a clock period
        #(CLK_PERIOD*4);

        // Directed test 3: reset held for many cycles, then released
        run_reset_pulse(2, CLK_PERIOD*6 + 3);
        #(CLK_PERIOD*4);

        // Randomized async assert/de-assert timing sweep
        for (i = 0; i < NUM_RANDOM_ITER; i = i + 1) begin
            run_reset_pulse(($unsigned($random) % 20) + 1, ($unsigned($random) % 30) + 1);
            #(CLK_PERIOD*3);
        end

        // ------------------------------------------------------------
        // Summary
        // ------------------------------------------------------------
        $display("========================================================");
        if (errors == 0)
            $display("*** ALL TESTS PASSED ***");
        else
            $display("*** %0d TEST(S) FAILED ***", errors);
        $display("========================================================");

        $finish;
    end

    // ------------------------------------------------------------
    // Safety timeout
    // ------------------------------------------------------------
    initial begin
        #(CLK_PERIOD * 1000);
        $display("[%0t] ERROR: Testbench timeout - simulation did not finish", $time);
        $finish;
    end

endmodule

Assignments/RST_SYNC/tb_RST_SYNC.vcd
$date
	Mon Aug 31 01:19:53 2026
$end
$version
	ModelSim Version 2020.1
$end
$timescale
	1ps
$end

$scope module tb_RST_SYNC $end
$var parameter 32 ! NUM_STAGES $end
$var parameter 32 " CLK_PERIOD $end
$var parameter 32 # NUM_RANDOM_ITER $end
$var reg 1 $ CLK $end
$var reg 1 % RST $end
$var wire 1 & SYNC_RST $end
$var integer 32 ' errors $end
$var integer 32 ( i $end
$var time 64 ) last_posedge_clk_time $end
$var time 64 * last_negedge_rst_time $end

$scope task run_reset_pulse $end
$var reg 32 + assert_offset [31:0] $end
$var reg 32 , hold_time [31:0] $end
$var integer 32 - cyc_count $end
$upscope $end

$scope module DUT $end
$var parameter 32 . NUM_STAGES $end
$var wire 1 / CLK $end
$var wire 1 0 RST $end
$var wire 1 & SYNC_RST $end
$var reg 2 1 Synchronizer [1:0] $end
$upscope $end
$upscope $end
$enddefinitions $end
#0
$dumpvars
0$
1%
bx 1
bx +
bx ,
b10 !
b1010 "
b1010 #
b10 .
b0 '
bx (
bx -
bx )
bx *
x&
10
0/
$end
#3000
b100 +
b10111 ,
#5000
1$
1/
b1x 1
b101 )
#7000
0%
00
b0 1
b111 *
0&
#10000
0$
0/
#15000
1$
1/
b1111 )
#20000
0$
0/
#25000
1$
1/
b11001 )
#30000
1%
b0 -
0$
10
0/
#35000
1$
1/
b10 1
b100011 )
#36000
b1 -
#40000
0$
0/
#45000
1$
1/
b11 1
b101101 )
1&
#46000
b10 -
#50000
0$
0/
#55000
1$
1/
b110111 )
#60000
0$
0/
#65000
1$
1/
b1000001 )
#70000
0$
0/
#75000
1$
1/
b1001011 )
#80000
0$
0/
#85000
1$
1/
b1010101 )
#86000
b111 +
b11 ,
#90000
0$
0/
#93000
0%
00
b0 1
b1011101 *
0&
#95000
1$
1/
b1011111 )
#96000
1%
b0 -
10
#100000
0$
0/
#105000
1$
1/
b10 1
b1101001 )
#106000
b1 -
#110000
0$
0/
#115000
1$
1/
b11 1
b1110011 )
1&
#116000
b10 -
#120000
0$
0/
#125000
1$
1/
b1111101 )
#130000
0$
0/
#135000
1$
1/
b10000111 )
#140000
0$
0/
#145000
1$
1/
b10010001 )
#150000
0$
0/
#155000
1$
1/
b10011011 )
#156000
b10 +
b111111 ,
#158000
0%
00
b0 1
b10011110 *
0&
#160000
0$
0/
#165000
1$
1/
b10100101 )
#170000
0$
0/
#175000
1$
1/
b10101111 )
#180000
0$
0/
#185000
1$
1/
b10111001 )
#190000
0$
0/
#195000
1$
1/
b11000011 )
#200000
0$
0/
#205000
1$
1/
b11001101 )
#210000
0$
0/
#215000
1$
1/
b11010111 )
#220000
0$
0/
#221000
1%
b0 -
10
#225000
1$
1/
b10 1
b11100001 )
#226000
b1 -
#230000
0$
0/
#235000
1$
1/
b11 1
b11101011 )
1&
#236000
b10 -
#240000
0$
0/
#245000
1$
1/
b11110101 )
#250000
0$
0/
#255000
1$
1/
b11111111 )
#260000
0$
0/
#265000
1$
1/
b100001001 )
#270000
0$
0/
#275000
1$
1/
b100010011 )
#276000
b0 (
b1001 +
b11100 ,
#280000
0$
0/
#285000
0%
1$
00
1/
b0 1
b100011101 )
b100011101 *
0&
#290000
0$
0/
#295000
1$
1/
b100100111 )
#300000
0$
0/
#305000
1$
1/
b100110001 )
#310000
0$
0/
#313000
1%
b0 -
10
#315000
1$
1/
b10 1
b100111011 )
#316000
b1 -
#320000
0$
0/
#325000
1$
1/
b11 1
b101000101 )
1&
#326000
b10 -
#330000
0$
0/
#335000
1$
1/
b101001111 )
#340000
0$
0/
#345000
1$
1/
b101011001 )
#350000
0$
0/
#355000
1$
1/
b101100011 )
#356000
b1 (
b10010 +
b10010 ,
#360000
0$
0/
#365000
1$
1/
b101101101 )
#370000
0$
0/
#374000
0%
00
b0 1
b101110110 *
0&
#375000
1$
1/
b101110111 )
#380000
0$
0/
#385000
1$
1/
b110000001 )
#390000
0$
0/
#392000
1%
b0 -
10
#395000
1$
1/
b10 1
b110001011 )
#396000
b1 -
#400000
0$
0/
#405000
1$
1/
b11 1
b110010101 )
1&
#406000
b10 -
#410000
0$
0/
#415000
1$
1/
b110011111 )
#420000
0$
0/
#425000
1$
1/
b110101001 )
#430000
0$
0/
#435000
1$
1/
b110110011 )
#436000
b10 (
#440000
0$
0/
#445000
1$
1/
b110111101 )
#450000
0$
0/
#454000
0%
00
b0 1
b111000110 *
0&
#455000
1$
1/
b111000111 )
#460000
0$
0/
#465000
1$
1/
b111010001 )
#470000
0$
0/
#472000
1%
b0 -
10
#475000
1$
1/
b10 1
b111011011 )
#476000
b1 -
#480000
0$
0/
#485000
1$
1/
b11 1
b111100101 )
1&
#486000
b10 -
#490000
0$
0/
#495000
1$
1/
b111101111 )
#500000
0$
0/
#505000
1$
1/
b111111001 )
#510000
0$
0/
#515000
1$
1/
b1000000011 )
#516000
b11 (
b110 +
b10111 ,
#520000
0$
0/
#522000
0%
00
b0 1
b1000001010 *
0&
#525000
1$
1/
b1000001101 )
#530000
0$
0/
#535000
1$
1/
b1000010111 )
#540000
0$
0/
#545000
1%
b0 -
1$
10
1/
b10 1
b1000100001 )
#546000
b1 -
#550000
0$
0/
#555000
1$
1/
b11 1
b1000101011 )
1&
#556000
b10 -
#560000
0$
0/
#565000
1$
1/
b1000110101 )
#570000
0$
0/
#575000
1$
1/
b1000111111 )
#580000
0$
0/
#585000
1$
1/
b1001001001 )
#586000
b100 (
b10 +
b10100 ,
#588000
0%
00
b0 1
b1001001100 *
0&
#590000
0$
0/
#595000
1$
1/
b1001010011 )
#600000
0$
0/
#605000
1$
1/
b1001011101 )
#608000
1%
b0 -
10
#610000
0$
0/
#615000
1$
1/
b10 1
b1001100111 )
#616000
b1 -
#620000
0$
0/
#625000
1$
1/
b11 1
b1001110001 )
1&
#626000
b10 -
#630000
0$
0/
#635000
1$
1/
b1001111011 )
#640000
0$
0/
#645000
1$
1/
b1010000101 )
#650000
0$
0/
#655000
1$
1/
b1010001111 )
#656000
b101 (
b10011 +
b10010 ,
#660000
0$
0/
#665000
1$
1/
b1010011001 )
#670000
0$
0/
#675000
0%
1$
00
1/
b0 1
b1010100011 )
b1010100011 *
0&
#680000
0$
0/
#685000
1$
1/
b1010101101 )
#690000
0$
0/
#693000
1%
b0 -
10
#695000
1$
1/
b10 1
b1010110111 )
#696000
b1 -
#700000
0$
0/
#705000
1$
1/
b11 1
b1011000001 )
1&
#706000
b10 -
#710000
0$
0/
#715000
1$
1/
b1011001011 )
#720000
0$
0/
#725000
1$
1/
b1011010101 )
#730000
0$
0/
#735000
1$
1/
b1011011111 )
#736000
b110 (
b1010 +
b10111 ,
#740000
0$
0/
#745000
1$
1/
b1011101001 )
#746000
0%
00
b0 1
b1011101010 *
0&
#750000
0$
0/
#755000
1$
1/
b1011110011 )
#760000
0$
0/
#765000
1$
1/
b1011111101 )
#769000
1%
b0 -
10
#770000
0$
0/
#775000
1$
1/
b10 1
b1100000111 )
#776000
b1 -
#780000
0$
0/
#785000
1$
1/
b11 1
b1100010001 )
1&
#786000
b10 -
#790000
0$
0/
#795000
1$
1/
b1100011011 )
#800000
0$
0/
#805000
1$
1/
b1100100101 )
#810000
0$
0/
#815000
1$
1/
b1100101111 )
#816000
b111 (
b111 ,
#820000
0$
0/
#825000
1$
1/
b1100111001 )
#826000
0%
00
b0 1
b1100111010 *
0&
#830000
0$
0/
#833000
1%
b0 -
10
#835000
1$
1/
b10 1
b1101000011 )
#836000
b1 -
#840000
0$
0/
#845000
1$
1/
b11 1
b1101001101 )
1&
#846000
b10 -
#850000
0$
0/
#855000
1$
1/
b1101010111 )
#860000
0$
0/
#865000
1$
1/
b1101100001 )
#870000
0$
0/
#875000
1$
1/
b1101101011 )
#876000
b1000 (
b10010 +
b1101 ,
#880000
0$
0/
#885000
1$
1/
b1101110101 )
#890000
0$
0/
#894000
0%
00
b0 1
b1101111110 *
0&
#895000
1$
1/
b1101111111 )
#900000
0$
0/
#905000
1$
1/
b1110001001 )
#907000
1%
b0 -
10
#910000
0$
0/
#915000
1$
1/
b10 1
b1110010011 )
#916000
b1 -
#920000
0$
0/
#925000
1$
1/
b11 1
b1110011101 )
1&
#926000
b10 -
#930000
0$
0/
#935000
1$
1/
b1110100111 )
#940000
0$
0/
#945000
1$
1/
b1110110001 )
#950000
0$
0/
#955000
1$
1/
b1110111011 )
#956000
b1001 (
b110 +
b10000 ,
#960000
0$
0/
#962000
0%
00
b0 1
b1111000010 *
0&
#965000
1$
1/
b1111000101 )
#970000
0$
0/
#975000
1$
1/
b1111001111 )
#978000
1%
b0 -
10
#980000
0$
0/
#985000
1$
1/
b10 1
b1111011001 )
#986000
b1 -
#990000
0$
0/
#995000
1$
1/
b11 1
b1111100011 )
1&
#996000
b10 -
#1000000
0$
0/
#1005000
1$
1/
b1111101101 )
#1010000
0$
0/
#1015000
1$
1/
b1111110111 )
#1020000
0$
0/
#1025000
1$
1/
b10000000001 )
#1026000
b1010 (
