Assignments/Assignment 2/Up_Dn_Counter.v
module Up_Dn_Counter(
    input [4:0] IN,
    input Load,Up,Down,CLK,
    output reg [4:0] Counter,
    output High,Low
);
    assign High = (Counter == 5'd31); 
    assign Low = (Counter == 5'd0);
    always @(posedge CLK) begin
        if(Load) begin
            Counter <= IN;
        end
        else if (Down && !Low) begin
            Counter <= Counter - 1;
        end
        else if (Up && !High) begin
            Counter <= Counter + 1;
        end
        else Counter <= Counter;
    end
endmodule

Assignments/Assignment 2/test_bench.v
module Up_Dn_Counter_TB;
    reg [4:0] IN_TB;
    reg Load_TB,Up_TB,Down_TB,CLK_TB;
    wire [4:0] Counter_TB;
    wire High_TB,Low_TB;
    Up_Dn_Counter DUT_Up_Dn_Counter (
        .IN(IN_TB),
        .Load(Load_TB),
        .Up(Up_TB),
        .Down(Down_TB),
        .CLK(CLK_TB),
        .Counter(Counter_TB),
        .High(High_TB),
        .Low(Low_TB)
    );
    initial begin
        CLK_TB = 0;
        forever begin
            #5 CLK_TB = ~CLK_TB;
        end
    end
    initial begin
        $dumpfile("Up_Dn_Counter_TB.vcd");
        $dumpvars;
    end
    initial begin
        $monitor("At Time: %0t,Counter: %0b,High Flag: %0b,Low Flag: %0b",$time,Counter_TB,High_TB,Load_TB);
    end
    initial fork 
        #0 {Load_TB,IN_TB} = 6'b110101;
        #10 {Load_TB,Down_TB,Up_TB} = 3'b111;
        #20 {Load_TB,Down_TB,Up_TB} = 3'b010;
        #30 {Load_TB,Down_TB,Up_TB} = 3'b011;
        #40 {Load_TB,Down_TB,Up_TB} = 3'b001;
        #50 {Load_TB,Down_TB,Up_TB} = 3'b000;
        #60 {Load_TB,IN_TB} = 6'b100001;
        #70 {Load_TB,Down_TB,Up_TB} = 3'b010;
        #110 {Load_TB,IN_TB} = 6'b111110;
        #130 {Load_TB,Down_TB,Up_TB} = 3'b001;
        #200 $finish;
    join
endmodule

Assignments/Assignment 2/Up_Dn_Counter_TB.vcd
$date
	Fri Jul 10 15:48:17 2026
$end
$version
	ModelSim Version 2020.1
$end
$timescale
	1ps
$end

$scope module Up_Dn_Counter_TB $end
$var reg 5 ! IN_TB [4:0] $end
$var reg 1 " Load_TB $end
$var reg 1 # Up_TB $end
$var reg 1 $ Down_TB $end
$var reg 1 % CLK_TB $end
$var wire 1 & Counter_TB [4] $end
$var wire 1 ' Counter_TB [3] $end
$var wire 1 ( Counter_TB [2] $end
$var wire 1 ) Counter_TB [1] $end
$var wire 1 * Counter_TB [0] $end
$var wire 1 + High_TB $end
$var wire 1 , Low_TB $end

$scope module DUT_Up_Dn_Counter $end
$var wire 1 - IN [4] $end
$var wire 1 . IN [3] $end
$var wire 1 / IN [2] $end
$var wire 1 0 IN [1] $end
$var wire 1 1 IN [0] $end
$var wire 1 2 Load $end
$var wire 1 3 Up $end
$var wire 1 4 Down $end
$var wire 1 5 CLK $end
$var reg 5 6 Counter [4:0] $end
$var wire 1 + High $end
$var wire 1 , Low $end
$upscope $end
$upscope $end
$enddefinitions $end
#0
$dumpvars
b10101 !
1"
x#
x$
0%
bx 6
x*
x)
x(
x'
x&
x+
x,
05
x4
x3
12
11
00
1/
0.
1-
$end
#5
1%
15
b10101 6
0,
0+
1*
0)
1(
0'
1&
#10
1#
1$
0%
13
14
05
#15
1%
15
#20
0#
0"
0%
03
02
05
#25
1%
15
b10100 6
0*
#30
1#
0%
13
05
#35
1%
15
b10011 6
1*
1)
0(
#40
0$
0%
04
05
#45
1%
15
b10100 6
0*
0)
1(
#50
0#
0%
03
05
#55
1%
15
#60
b1 !
1"
0%
0/
0-
12
05
#65
1%
15
b1 6
1*
0(
0&
#70
1$
0"
0%
14
02
05
#75
1%
15
b0 6
1,
0*
#80
0%
05
#85
1%
15
#90
0%
05
#95
1%
15
#100
0%
05
#105
1%
15
#110
b11110 !
1"
0%
01
10
1/
1.
1-
12
05
#115
1%
15
b11110 6
0,
1)
1(
1'
1&
#120
0%
05
#125
1%
15
#130
1#
0$
0"
0%
13
04
02
05
#135
1%
15
b11111 6
1+
1*
